Workbook

Sheet 1. Raw Data - Bloomberg
B2: Starbucks Corp (SBUX US) - BBG Adjusted
B3: In Millions of USD except Per Share | C3: In Millions of USD except Per Share | D3: FY 2015 | E3: FY 2016 | F3: FY 2017 | G3: FY 2018 | H3: FY 2019 | I3: FY 2020 | J3: FY 2021 | K3: FY 2022 | L3: FY 2023 | M3: FY 2024
B4: 12 Months Ending | C4: 12 Months Ending | D4: 09/27/2015 | E4: 10/02/2016 | F4: 10/01/2017 | G4: 09/30/2018 | H4: 09/29/2019 | I4: 09/27/2020 | J4: 10/03/2021 | K4: 10/02/2022 | L4: 10/01/2023 | M4: 09/29/2024
B5: Revenue | C5: Revenue | D5: 19162.7 | E5: 21315.9 | F5: 22386.8 | G5: 24719.5 | H5: 26508.6 | I5: 23518 | J5: 29060.6 | K5: 32250.3 | L5: 35975.6 | M5: 36176.2
B6: + Sales & Services Revenue | C6: + Sales & Services Revenue | D6: 17300.8 | E6: 19161.7 | F6: 20005.7 | G6: 22067.3 | H6: 23633.6 | I6: 21190.9 | J6: 26377 | K6: 28594.8 | L6: 31462.9 | M6: 31671.1 | AD6: Income Statement
B7: + Other Revenue | C7: + Other Revenue | D7: 1861.9 | E7: 2154.2 | F7: 2381.1 | G7: 2652.2 | H7: 2875 | I7: 2327.1 | J7: 2683.6 | K7: 3655.5 | L7: 4512.7 | M7: 4505.1
B8: - Cost of Revenue | C8: - Cost of Revenue | D8: 13198.6 | E8: 14573.3 | F8: 15552.2 | G8: 17402.9 | H8: 19020.5 | I8: 18458.9 | J8: 20652 | K8: 23879.2 | L8: 26129.4 | M8: 26467.1 | AD8: Balance Sheet
B9: + Cost of Goods & Services | C9: + Cost of Goods & Services | D9: 13198.6 | E9: 14573.3 | F9: 15552.2 | G9: 17402.9 | H9: 19020.5 | I9: 18458.9 | J9: 20652 | K9: 23879.2 | L9: 26129.4 | M9: 26467.1 | AD9: Cashflow Statement
B10: Gross Profit | C10: Gross Profit | D10: 5964.1 | E10: 6742.6 | F10: 6834.6 | G10: 7316.6 | H10: 7488.1 | I10: 5059.1 | J10: 8408.6 | K10: 8371.1 | L10: 9846.2 | M10: 9709.1 | AD10: Revenue Break-up
B11: + Other Operating Income | C11: + Other Operating Income | D11: 0 | E11: 318.2 | F11: 391.4 | G11: 301.2 | H11: 298 | I11: 322.5 | J11: 385.3 | K11: 234.1 | L11: 298.4 | M11: 301.2 | AD11: Additional Information
B12: - Operating Expenses | C12: - Operating Expenses | D12: 2308.5 | E12: 2888.9 | F12: 2874.8 | G12: 3122.8 | H12: 3215.6 | I12: 3248.4 | J12: 3576 | K12: 3750.2 | L12: 4343.2 | M12: 4480
B13: + Selling, General & Admin | C13: + Selling, General & Admin | D13: 1424.6 | E13: 1657.5 | F13: 1691 | G13: 1968.5 | H13: 2029 | I13: 1922.2 | J13: 2215.5 | K13: 2448.7 | L13: 2949.1 | M13: 2523.3
B14: + Selling & Marketing | C14: + Selling & Marketing | D14: 227.9 | E14: 248.6 | F14: 282.6 | G14: 260.3 | H14: 245.7 | I14: 258.8 | J14: 305.1 | K14: 416.7 | L14: 507.8 | M14: 0
B15: + General & Administrative | C15: + General & Administrative | D15: 1196.7 | E15: 1408.9 | F15: 1408.4 | G15: 1708.2 | H15: 1783.3 | I15: 1663.4 | J15: 1910.4 | K15: 2032 | L15: 2441.3 | M15: 2523.3
B16: + Research & Development | C16: + Research & Development | D16: 0 | E16: 0 | F16: 0 | G16: 0 | H16: 0 | I16: 0 | J16: 0 | K16: 0 | L16: 0 | M16: 0
B17: + Depreciation & Amortization | C17: + Depreciation & Amortization | D17: 893.9 | E17: 980.8 | F17: 1011.4 | G17: 1247 | H17: 1377.3 | I17: 1431.3 | J17: 1441.7 | K17: 1447.9 | L17: 1362.6 | M17: 1512.6
B18: + Other Operating Expense | C18: + Other Operating Expense | D18: -10 | E18: 250.6 | F18: 172.4 | G18: -92.7 | H18: -190.7 | I18: -105.1 | J18: -81.2 | K18: -146.4 | L18: 31.5 | M18: 444.1
B19: Operating Income (Loss) | C19: Operating Income (Loss) | D19: 3655.6 | E19: 4171.9 | F19: 4351.2 | G19: 4495 | H19: 4570.5 | I19: 2133.2 | J19: 5217.9 | K19: 4855 | L19: 5801.4 | M19: 5530.3
B20: - Non-Operating (Income) Loss | C20: - Non-Operating (Income) Loss | D20: 27.5 | E20: -21.3 | F20: -89.3 | G20: -21.1 | H20: 234.5 | I20: 397.3 | J20: 379.7 | K20: 385.9 | L20: 468.9 | M20: 439.2
B21: + Interest Expense, Net | C21: + Interest Expense, Net | D21: 0 | E21: 0 | F21: 0 | G21: 0 | H21: 0 | I21: 0 | J21: 0 | K21: 482.9 | L21: 550.1 | M21: 562
B22: + Interest Expense | C22: + Interest Expense | D22: 70.5 | E22: 81.3 | F22: 92.5 | G22: 170.3 | H22: 331 | I22: 437 | J22: 469.8 | K22: 482.9 | L22: 550.1 | M22: 562
B23: - Interest Income | C23: - Interest Income | D23: 0 | E23: 0 | F23: 0 | G23: 0 | H23: 0 | I23: 0 | J23: 0 | K23: 0 | L23: 0 | M23: 0
... B64: Diluted EPS from Cont Ops, Adjusted | C64: Diluted EPS from Cont Ops, Adjusted | D64: 1.7019 | E64: 1.8976 | F64: 2.0456 | G64: 2.6924 | H64: 2.8384 | I64: 1.172 | J64: 3.1943 | K64: 2.9918 | L64: 3.5324 | M64: 3.3944
B66: Reference Items | C66: Reference Items
B67: Accounting Standard | C67: Accounting Standard | D67: US GAAP | E67: US GAAP | F67: US GAAP | G67: US GAAP | H67: US GAAP | I67: US GAAP | J67: US GAAP | K67: US GAAP | L67: US GAAP | M67: US GAAP
B68: EBITDA | C68: EBITDA | D68: 4589.4 | E68: 5202 | F68: 5418.3 | G68: 5800.9 | H68: 6019.8 | I68: 5210 | J68: 8321.2 | K68: 7939.2 | L68: 8852.7 | M68: 8846.2
B69: EBITDA Margin (T12M) | C69: EBITDA Margin (T12M) | D69: 23.9497 | E69: 24.4043 | F69: 24.2031 | G69: 23.4669 | H69: 22.7089 | I69: 22.1532 | J69: 28.634 | K69: 24.6174 | L69: 24.6075 | M69: 24.4531
B70: EBITA | C70: EBITA | D70: 3745.5 | E70: 4278.5 | F70: 4464.4 | G70: 4740.4 | H70: 4875.3 | I70: 4002.4 | J70: 7102.9 | K70: 6684 | L70: 7511.6 | M70: 7354
B71: EBIT | C71: EBIT | D71: 3655.6 | E71: 4171.9 | F71: 4351.2 | G71: 4495 | H71: 4570.5 | I71: 2133.2 | J71: 5217.9 | K71: 4855 | L71: 5801.4 | M71: 5530.3
B72: Gross Margin | C72: Gross Margin | D72: 31.1235 | E72: 31.6318 | F72: 30.5296 | G72: 29.5985 | H72: 28.2478 | I72: 21.5116 | J72: 28.9347 | K72: 25.9567 | L72: 27.3691 | M72: 26.8384
B73: Operating Margin | C73: Operating Margin | D73: 19.0766 | E73: 19.5718 | F73: 19.4365 | G73: 18.184 | H73: 17.2416 | I73: 9.0705 | J73: 17.9552 | K73: 15.0541 | L73: 16.1259 | M73: 15.2871
B74: Profit Margin | C74: Profit Margin | D74: 13.457 | E74: 13.2023 | F74: 13.3792 | G74: 15.1887 | H74: 13.1978 | I74: 5.8669 | J74: 13.0401 | K74: 10.7565 | L74: 11.3123 | M74: 10.6614
B75: Sales per Employee | C75: Sales per Employee | D75: 80515.546 | E75: 83920.866 | F75: 80818.773 | G75: 84946.735 | H75: 76614.451 | I75: 67386.819 | J75: 75876.24 | K75: 80224.627 | L75: 94424.147 | M75: 100211.08
B76: Dividends per Share | C76: Dividends per Share | D76: 0.68 | E76: 0.85 | F76: 1.05 | G76: 1.32 | H76: 1.49 | I76: 1.68 | J76: 1.84 | K76: 1.96 | L76: 2.12 | M76: 2.32
B77: Total Cash Common Dividends | C77: Total Cash Common Dividends | D77: 1016.2 | E77: 1246.2 | F77: 1521.975 | G77: 1825.164 | H77: 1819.588 | I77: 1970.304 | J77: 2166.784 | K77: 2260.468 | L77: 2431.216 | M77: 2630.416
B78: Capitalized Interest Expense | C78: Capitalized Interest Expense | D78: 3.6 | E78: 0 | F78: 0 | G78: 0 | H78: 0 | I78: 0 | J78: 0 | K78: 0 | L78: 0 | M78: 0
B79: Depreciation Expense | C79: Depreciation Expense | D79: 843.9 | E79: 923.5 | F79: 953.9 | G79: 1060.5 | H79: 1144.5 | I79: 1207.6 | J79: 1218.3 | K79: 1255.2 | L79: 1341.1 | M79: 1492.2
B80: Rental Expense | C80: Rental Expense | D80: 1137.8 | E80: 1223.2 | F80: 1329.2 | G80: 1625.2 | H80: 1666 | I80: 2441.1 | J80: 2559.7 | K80: 2522 | L80: 2679.3 | M80: 2881
B81: Source: Bloomberg
B84: Starbucks Corp (SBUX US) - Standardized
B85: In Millions of USD except Per Share | D85: FY 2015 | E85: FY 2016 | F85: FY 2017 | G85: FY 2018 | H85: FY 2019 | I85: FY 2020 | J85: FY 2021 | K85: FY 2022 | L85: FY 2023 | M85: FY 2024
B86: 12 Months Ending | D86: 09/27/2015 | E86: 10/02/2016 | F86: 10/01/2017 | G86: 09/30/2018 | H86: 09/29/2019 | I86: 09/27/2020 | J86: 10/03/2021 | K86: 10/02/2022 | L86: 10/01/2023 | M86: 09/29/2024
B87: Total Assets
B88: + Cash, Cash Equivalents & STI | D88: 1611.4 | E88: 2263.2 | F88: 2690.9 | G88: 8937.8 | H88: 2757.1 | I88: 4632.1 | J88: 6617.9 | K88: 3182.9 | L88: 3953 | M88: 3543.2
B89: + Cash & Cash Equivalents | D89: 1530.1 | E89: 2128.8 | F89: 2462.3 | G89: 8756.3 | H89: 2686.6 | I89: 4350.9 | J89: 6455.7 | K89: 2818.4 | L89: 3551.5 | M89: 3286.2
B90: + ST Investments | D90: 81.3 | E90: 134.4 | F90: 228.6 | G90: 181.5 | H90: 70.5 | I90: 281.2 | J90: 162.2 | K90: 364.5 | L90: 401.5 | M90: 257
B91: + Accounts & Notes Receiv | D91: 719 | E91: 768.8 | F91: 870.4 | G91: 693.1 | H91: 879.2 | I91: 883.4 | J91: 940 | K91: 1175.5 | L91: 1184.1 | M91: 1213.8
B92: + Accounts Receivable, Net | D92: 719 | E92: 768.8 | F92: 870.4 | G92: 693.1 | H92: 879.2 | I92: 883.4 | J92: 940 | K92: 1175.5 | L92: 1184.1 | M92: 1213.8
B93: + Notes Receivable, Net | D93: 0 | E93: 0 | F93: 0 | G93: 0 | H93: 0 | I93: 0 | J93: 0 | K93: 0 | L93: 0 | M93: 0
B94: + Inventories | D94: 1306.4 | E94: 1378.5 | F94: 1364 | G94: 1400.5 | H94: 1529.4 | I94: 1551.4 | J94: 1603.9 | K94: 2176.6 | L94: 1806.4 | M94: 1777.3
B95: + Raw Materials | D95: 809.1 | E95: 862 | F95: 842.1 | G95: 869.8 | H95: 933 | I95: 888.2 | J95: 903.8 | K95: 1328.9 | L95: 1028 | M95: 917
B96: + Work In Process | D96: 0 | E96: 0 | F96: 0 | G96: 0 | H96: 0 | I96: 0 | J96: 0 | K96: 0 | L96: 0 | M96: 0
B97: + Finished Goods | D97: 318.3 | E97: 308.6 | F97: 301.1 | G97: 273.1 | H97: 288 | I97: 293.9 | J97: 329.3 | K97: 430.9 | L97: 364.6 | M97: 384.6
B98: + Other Inventory | D98: 179 | E98: 207.9 | F98: 220.8 | G98: 257.6 | H98: 308.4 | I98: 369.3 | J98: 370.8 | K98: 416.8 | L98: 413.8 | M98: 475.7
B99: + Other ST Assets | D99: 334.2 | E99: 350 | F99: 358.1 | G99: 1462.8 | H99: 488.2 | I99: 739.5 | J99: 594.6 | K99: 483.7 | L99: 359.9 | M99: 313.1
... B104: Total Current Assets | D104: 3971 | E104: 4760.5 | F104: 5283.4 | G104: 12494.2 | H104: 5653.9 | I104: 7806.4 | J104: 9756.4 | K104: 7018.7 | L104: 7303.4 | M104: 6847.4
B105: + Property, Plant & Equip, Net | C105: =D106-D107 -> 4088.3 | D105: 4088.3 | E105: 4533.8 | F105: 4919.5 | G105: 5929.1 | H105: 6431.7 | I105: 14375.5 | J105: 14605.5 | K105: 14576.1 | L105: 15799.7 | M105: 17951.7
B106: + Property, Plant & Equip | D106: 9641.8 | E106: 10573.3 | F106: 11584 | G106: 13197.1 | H106: 14273.5 | I106: 22289.4 | J106: 23064.8 | K106: 23625.4 | L106: 25722.8 | M106: 28727.2
B107: - Accumulated Depreciation | D107: 5553.5 | E107: 6039.5 | F107: 6664.5 | G107: 7268 | H107: 7841.8 | I107: 7913.9 | J107: 8459.3 | K107: 9049.3 | L107: 9923.1 | M107: 10775.5
B108: + LT Investments & Receivables | C108: =D109 -> 312.5 | D108: 312.5 | E108: 1141.7 | F108: 542.3 | G108: 267.7 | H108: 220 | I108: 206.1 | J108: 281.7 | K108: 279.1 | L108: 247.4 | M108: 276
B109: + LT Investments | D109: 312.5 | E109: 1141.7 | F109: 542.3 | G109: 267.7 | H109: 220 | I109: 206.1 | J109: 281.7 | K109: 279.1 | L109: 247.4 | M109: 276
B110: + Other LT Assets | D110: 4044.5 | E110: 3893.5 | F110: 3620.4 | G110: 5465.4 | H110: 6914 | I110: 6986.5 | J110: 6749 | K110: 6104.5 | L110: 6095 | M110: 6264.2
B111: + Total Intangible Assets | D111: 2095.8 | E111: 2235.9 | F111: 1980.6 | G111: 4583.8 | H111: 4272.6 | I111: 4149.3 | J111: 4027.2 | K111: 3439.4 | L111: 3338.8 | M111: 3416.6
B112: + Goodwill | D112: 1575.4 | E112: 1719.6 | F112: 1539.2 | G112: 3541.6 | H112: 3490.8 | I112: 3597.2 | J112: 3677.3 | K112: 3283.5 | L112: 3218.3 | M112: 3315.7
B113: + Other Intangible Assets | D113: 520.4 | E113: 516.3 | F113: 441.4 | G113: 1042.2 | H113: 781.8 | I113: 552.1 | J113: 349.9 | K113: 155.9 | L113: 120.5 | M113: 100.9
B114: + Deferred Tax Assets | D114: 1180.8 | E114: 885.4 | F114: 795.4 | G114: 134.7 | H114: 1765.8 | I114: 1789.9 | J114: 1874.8 | K114: 1799.7 | L114: 1769.8 | M114: 1766.7
B115: + Derivative & Hedging Assets | D115: 54.7 | E115: 6.4 | F115: 13.4 | G115: 24.5 | H115: 26.3 | I115: 87.3 | J115: 84.3 | K115: 156.2 | L115: 153 | M115: 183
B116: + Prepaid Pension Costs | D116: 352 | E116: 354.5 | F116: 481.6 | G116: 334.7 | H116: 396 | I116: 478.7 | J116: 268.5 | K116: 311.2 | L116: 439.9 | M116: 463.9
B117: + Misc LT Assets | D117: 361.2 | E117: 411.3 | F117: 349.4 | G117: 387.7 | H117: 453.3 | I117: 481.3 | J117: 494.2 | K117: 398 | L117: 393.5 | M117: 434
B118: Total Noncurrent Assets | D118: 8445.3 | E118: 9569 | F118: 9082.2 | G118: 11662.2 | H118: 13565.7 | I118: 21568.1 | J118: 21636.2 | K118: 20959.7 | L118: 22142.1 | M118: 24491.9
B119: Total Assets | D119: 12416.3 | E119: 14329.5 | F119: 14365.6 | G119: 24156.4 | H119: 19219.6 | I119: 29374.5 | J119: 31392.6 | K119: 27978.4 | L119: 29445.5 | M119: 31339.3
B121: Liabilities & Shareholders' Equity
B122: + Payables & Accruals | D122: 2420.3 | E122: 2711.7 | F122: 2700.6 | G122: 3684.9 | H122: 4894 | I122: 2945.5 | J122: 4296.5 | K122: 4458.4 | L122: 4514.1 | M122: 4565.2
B123: + Accounts Payable | D123: 684.2 | E123: 730.6 | F123: 782.5 | G123: 1179.3 | H123: 1189.7 | I123: 997.9 | J123: 1211.6 | K123: 1441.4 | L123: 1544.3 | M123: 1595.5
B124: + Accrued Taxes | D124: 259 | E124: 368.4 | F124: 226.6 | G124: 286.6 | H124: 1468.4 | I124: 260.9 | J124: 566 | K124: 333.8 | L124: 212.7 | M124: 211.2
B125: + Interest & Dividends Payable | D125: 0 | E125: 0 | F125: 0 | G125: 445.4 | H125: 485.7 | I125: 0 | J125: 578.1 | K125: 608.3 | L125: 651.2 | M125: 691.2
B126: + Other Payables & Accruals | D126: 1477.1 | E126: 1612.7 | F126: 1691.5 | G126: 1773.6 | H126: 1750.2 | I126: 1686.7 | J126: 1940.8 | K126: 2074.9 | L126: 2105.9 | M126: 2067.3
B127: + ST Debt | D127: 0 | E127: 400 | F127: 0 | G127: 349.9 | H127: 0 | I127: 2937.5 | J127: 2250.2 | K127: 3169.7 | L127: 3127.4 | M127: 2712
B128: + ST Borrowings | D128: 0 | E128: 0 | F128: 0 | G128: 0 | H128: 0 | I128: 438.8 | J128: 0 | K128: 175 | L128: 33.5 | M128: 0
B129: + ST Lease Liabilities | D129: 0 | E129: 0 | F129: 0 | G129: 0 | H129: 0 | I129: 1248.8 | J129: 1251.3 | K129: 1245.7 | L129: 1275.3 | M129: 1463.1
B130: + ST Finance Leases | D130: 0 | E130: 0 | F130: 0 | G130: 0 | H130: 0 | I130: 0 | J130: 0 | K130: 0 | L130: 0 | M130: 0
B131: + ST Operating Leases | D131: 0 | E131: 0 | F131: 0 | G131: 0 | H131: 0 | I131: 1248.8 | J131: 1251.3 | K131: 1245.7 | L131: 1275.3 | M131: 1463.1
B132: + Current Portion of LT Debt | D132: 0 | E132: 400 | F132: 0 | G132: 349.9 | H132: 0 | I132: 1249.9 | J132: 998.9 | K132: 1749 | L132: 1818.6 | M132: 1248.9
B133: + Other ST Liabilities | D133: 1227.8 | E133: 1435.2 | F133: 1520.1 | G133: 1649.4 | H133: 1274.7 | I133: 1463.8 | J133: 1604.7 | K133: 1523.7 | L133: 1703.8 | M133: 1792.8
... B164: Total Liabilities & Equity | D164: 12416.3 | E164: 14329.5 | F164: 14365.6 | G164: 24156.4 | H164: 19219.6 | I164: 29374.5 | J164: 31392.6 | K164: 27978.4 | L164: 29445.5 | M164: 31339.3
B166: Reference Items
B167: Accounting Standard | D167: US GAAP | E167: US GAAP | F167: US GAAP | G167: US GAAP | H167: US GAAP | I167: US GAAP | J167: US GAAP | K167: US GAAP | L167: US GAAP | M167: US GAAP
B168: Shares Outstanding | D168: 1485.1 | E168: 1460.5 | F168: 1431.6 | G168: 1309.1 | H168: 1184.6 | I168: 1173.3 | J168: 1180 | K168: 1147.9 | L168: 1142.6 | M168: 1133.5
B169: Number of Treasury Shares | D169: 0 | E169: 0 | F169: 0 | G169: 0 | H169: 0 | I169: 0 | J169: 0 | K169: 0 | L169: 0 | M169: 0
B170: Pension Obligations | D170: 0 | E170: 0 | F170: 0 | G170: 0 | H170: 0 | I170: 0 | J170: 0 | K170: 0 | L170: 0 | M170: 0
B171: Future Minimum Operating Lease Obligations | D171: 5657.6 | E171: 7270.4 | F171: 8598 | G171: 9353.8 | H171: 10230.9 | I171: 10089.6 | J171: 10129.9 | K171: 9863.7 | L171: 10594.1 | M171: 11942.3
B172: Capital Leases - Total | D172: 0 | E172: 0 | F172: 0 | G172: 0 | H172: 0 | I172: 0 | J172: 0 | K172: 0 | L172: 0 | M172: 0
B173: Options Granted During Period | D173: 6.4 | E173: 6.1 | F173: 7.1 | G173: 3.9 | H173: 0.5 | I173: 0.1 | J173: 0 | K173: 0 | L173: 0 | M173: 0
B174: Options Outstanding at Period End | D174: 33.6 | E174: 31.3 | F174: 31.4 | G174: 27.3 | H174: 15.2 | I174: 9.2 | J174: 5.2 | K174: 4.1 | L174: 2 | M174: 0.9
B175: Net Debt | D175: 736.1 | E175: 1339 | F175: 1241.7 | G175: 502.3 | H175: 8409.9 | I175: 20626.7 | J175: 16987.2 | K175: 20621.9 | L175: 20646.8 | M175: 22259.9
B176: Net Debt to Equity | D176: 12.6482 | E176: 22.7307 | F176: 22.7543 | G176: 42.7199 | H176: 0 | I176: 0 | J176: 0 | K176: 0 | L176: 0 | M176: 0
B177: Tangible Common Equity Ratio | D177: 36.0661 | E177: 30.1655 | F177: 28.0137 | G177: -17.4443 | H177: -70.2803 | I177: -47.3907 | J177: -34.1614 | K177: -49.4967 | L177: -43.4126 | M177: -38.9128
B178: Current Ratio | D178: 1.0885 | E178: 1.047 | F178: 1.2518 | G178: 2.1981 | H178: 0.9165 | I178: 1.0626 | J178: 1.1969 | K178: 0.7669 | L178: 0.7815 | M178: 0.755
B179: Cash Conversion Cycle | D179: 29.3547 | E179: 29.2029 | F179: 27.6969 | G179: 19.949 | H179: 16.3146 | I179: 22.4727 | J179: 20.1775 | K179: 21.0056 | L179: 18.5848 | M179: 15.0924
... B181: Number of Employees | D181: 238000 | E181: 254000 | F181: 277000 | G181: 291000 | H181: 346000 | I181: 349000 | J181: 383000 | K181: 402000 | L181: 381000 | M181: 361000
...

Sheet 2. Integrated Finance
B2: Integrated Finance - Starbucks Corp
B5: INCOME STATEMENT
A6: # | B6: PARTICULARS | C6: ACTUALS | M6: NEAR TERM FORECAST | R6: FAR TERM FORECAST | AB6: CV
C7: =2015 -> 2015 | D7: =C7+1 -> 2016 | E7: =D7+1 -> 2017 | F7: =E7+1 -> 2018 | G7: =F7+1 -> 2019 | H7: =G7+1 -> 2020 | I7: =H7+1 -> 2021 | J7: =I7+1 -> 2022 | K7: =J7+1 -> 2023 | ... BV7: =BU7+1 -> 2086
C8: ="FY "&C7 -> FY 2015 | D8: ="FY "&D7 -> FY 2016 | E8: ="FY "&E7 -> FY 2017 | F8: ="FY "&F7 -> FY 2018 | G8: ="FY "&G7 -> FY 2019 | H8: ="FY "&H7 -> FY 2020 | I8: ="FY "&I7 -> FY 2021 | J8: ="FY "&J7 -> FY 2022 | ... AA8: ="FY "&AA7 -> FY 2039 | AB8: Perpetuity
B9: Revenue | C9: ='1. Raw Data - Bloomberg'!D5 -> 19162.7 | D9: ='1. Raw Data - Bloomberg'!E5 -> 21315.9 | E9: ='1. Raw Data - Bloomberg'!F5 -> 22386.8 | F9: ='1. Raw Data - Bloomberg'!G5 -> 24719.5 | G9: ='1. Raw Data - Bloomberg'!H5 -> 26508.6 | H9: ='1. Raw Data - Bloomberg'!I5 -> 23518 | I9: ='1. Raw Data - Bloomberg'!J5 -> 29060.6 | J9: ='1. Raw Data - Bloomberg'!K5 -> 32250.3 | ... L9: ='1. Raw Data - Bloomberg'!M5 -> 36176.2 | M9: =M10+M12+M11 -> 39113.905 | N9: =N10+N12+N11 -> 42309.723 | O9: =O10+O12+O11 -> 45786.613 | P9: =P10+P12+P11 -> 49569.62 | Q9: =Q10+Q12+Q11 -> 53686.068 | R9: =R10+R12+R11 -> 58165.776 | S9: =S10+S12+S11 -> 63041.287 | T9: =T10+T12+T11 -> 68348.127 | ... AB9: =AB10+AB12+AB11 -> 131826.12
B10: Company Operated Retail | C10: ='1. Raw Data - Bloomberg'!D260 -> 15197.3 | D10: ='1. Raw Data - Bloomberg'!E260 -> 16844.1 | E10: ='1. Raw Data - Bloomberg'!F260 -> 17650.7 | F10: ='1. Raw Data - Bloomberg'!G260 -> 19690.3 | G10: ='1. Raw Data - Bloomberg'!H260 -> 21544.4 | H10: ='1. Raw Data - Bloomberg'!I260 -> 19164.6 | I10: ='1. Raw Data - Bloomberg'!J260 -> 24607 | J10: ='1. Raw Data - Bloomberg'!K260 -> 26576.1 | ... L10: ='1. Raw Data - Bloomberg'!M260 -> 29765.9 | M10: =L10*(1+'3. Historical & Forecast Ratio '!M10) -> 32208.072 | N10: =M10*(1+'3. Historical & Forecast Ratio '!N10) -> 34850.615 | O10: =N10*(1+'3. Historical & Forecast Ratio '!O10) -> 37709.968 | P10: =O10*(1+'3. Historical & Forecast Ratio '!P10) -> 40803.919 | Q10: =P10*(1+'3. Historical & Forecast Ratio '!Q10) -> 44151.717 | R10: =Q10*(1+'3. Historical & Forecast Ratio '!R10) -> 47774.188 | S10: =R10*(1+'3. Historical & Forecast Ratio '!S10) -> 51693.868 | T10: =S10*(1+'3. Historical & Forecast Ratio '!T10) -> 55935.141 | ... AB10: =AA10*(1+'3. Historical & Forecast Ratio '!AB10) -> 105111.56
B11: Licensed Stores | C11: ='1. Raw Data - Bloomberg'!D268 -> 1861.9 | D11: ='1. Raw Data - Bloomberg'!E268 -> 2154.2 | E11: ='1. Raw Data - Bloomberg'!F268 -> 2355 | F11: ='1. Raw Data - Bloomberg'!G268 -> 2652.2 | G11: ='1. Raw Data - Bloomberg'!H268 -> 2875 | H11: ='1. Raw Data - Bloomberg'!I268 -> 2327.1 | I11: ='1. Raw Data - Bloomberg'!J268 -> 2683.6 | J11: ='1. Raw Data - Bloomberg'!K268 -> 3655.5 | ... L11: ='1. Raw Data - Bloomberg'!M268 -> 4505.1 | M11: =L11*(1+'3. Historical & Forecast Ratio '!M11) -> 5014.6791 | N11: =M11*(1+'3. Historical & Forecast Ratio '!N11) -> 5581.8974 | O11: =N11*(1+'3. Historical & Forecast Ratio '!O11) -> 6213.2748 | P11: =O11*(1+'3. Historical & Forecast Ratio '!P11) -> 6916.0682 | Q11: =P11*(1+'3. Historical & Forecast Ratio '!Q11) -> 7698.3557 | R11: =Q11*(1+'3. Historical & Forecast Ratio '!R11) -> 8569.129 | S11: =R11*(1+'3. Historical & Forecast Ratio '!S11) -> 9538.3969 | T11: =S11*(1+'3. Historical & Forecast Ratio '!T11) -> 10617.3 | ... AB11: =AA11*(1+'3. Historical & Forecast Ratio '!AB11) -> 25022.1
B12: CPG, Foodservice and Other | C12: ='1. Raw Data - Bloomberg'!D270 -> 2103.5 | D12: ='1. Raw Data - Bloomberg'!E270 -> 2317.6 | E12: ='1. Raw Data - Bloomberg'!F270 -> 2381.1 | F12: ='1. Raw Data - Bloomberg'!G270 -> 2377 | G12: ='1. Raw Data - Bloomberg'!H270 -> 2089.2 | H12: ='1. Raw Data - Bloomberg'!I270 -> 2026.3 | I12: ='1. Raw Data - Bloomberg'!J270 -> 1770 | J12: ='1. Raw Data - Bloomberg'!K270 -> 2018.7 | ... L12: ='1. Raw Data - Bloomberg'!M270 -> 1905.2 | M12: =L12*(1+'3. Historical & Forecast Ratio '!M12) -> 1891.1535 | N12: =M12*(1+'3. Historical & Forecast Ratio '!N12) -> 1877.2106 | O12: =N12*(1+'3. Historical & Forecast Ratio '!O12) -> 1863.3704 | P12: =O12*(1+'3. Historical & Forecast Ratio '!P12) -> 1849.6324 | Q12: =P12*(1+'3. Historical & Forecast Ratio '!Q12) -> 1835.9955 | R12: =Q12*(1+'3. Historical & Forecast Ratio '!R12) -> 1822.4593 | S12: =R12*(1+'3. Historical & Forecast Ratio '!S12) -> 1809.0228 | T12: =S12*(1+'3. Historical & Forecast Ratio '!T12) -> 1795.6854 | ... AB12: =AA12*(1+'3. Historical & Forecast Ratio '!AB12) -> 1692.4659
B13: COGS | C13: ='1. Raw Data - Bloomberg'!D9 -> 13198.6 | D13: ='1. Raw Data - Bloomberg'!E9 -> 14573.3 | E13: ='1. Raw Data - Bloomberg'!F9 -> 15552.2 | F13: ='1. Raw Data - Bloomberg'!G9 -> 17402.9 | G13: ='1. Raw Data - Bloomberg'!H9 -> 19020.5 | H13: ='1. Raw Data - Bloomberg'!I9 -> 18458.9 | I13: ='1. Raw Data - Bloomberg'!J9 -> 20652 | J13: ='1. Raw Data - Bloomberg'!K9 -> 23879.2 | ... L13: ='1. Raw Data - Bloomberg'!M9 -> 26467.1 | M13: =M9*'3. Historical & Forecast Ratio '!M13 -> 28093.89 | N13: =N9*'3. Historical & Forecast Ratio '!N13 -> 30389.313 | O13: =O9*'3. Historical & Forecast Ratio '!O13 -> 32886.619 | P13: =P9*'3. Historical & Forecast Ratio '!P13 -> 35603.795 | Q13: =Q9*'3. Historical & Forecast Ratio '!Q13 -> 38560.468 | R13: =R9*'3. Historical & Forecast Ratio '!R13 -> 41778.056 | S13: =S9*'3. Historical & Forecast Ratio '!S13 -> 45279.933 | T13: =T9*'3. Historical & Forecast Ratio '!T13 -> 49091.615 | ... AB13: =AB9*'3. Historical & Forecast Ratio '!AB13 -> 94685.216
B15: Gross Profit | C15: =C9-C13 -> 5964.1 | D15: =D9-D13 -> 6742.6 | E15: =E9-E13 -> 6834.6 | F15: =F9-F13 -> 7316.6 | G15: =G9-G13 -> 7488.1 | H15: =H9-H13 -> 5059.1 | I15: =I9-I13 -> 8408.6 | J15: =J9-J13 -> 8371.1 | ... AB15: =AB9-AB13 -> 37140.905
B17: Other Operating Income | C17: ='1. Raw Data - Bloomberg'!D11 -> 0 | D17: ='1. Raw Data - Bloomberg'!E11 -> 318.2 | E17: ='1. Raw Data - Bloomberg'!F11 -> 391.4 | F17: ='1. Raw Data - Bloomberg'!G11 -> 301.2 | G17: ='1. Raw Data - Bloomberg'!H11 -> 298 | H17: ='1. Raw Data - Bloomberg'!I11 -> 322.5 | I17: ='1. Raw Data - Bloomberg'!J11 -> 385.3 | J17: ='1. Raw Data - Bloomberg'!K11 -> 234.1 | ... L17: ='1. Raw Data - Bloomberg'!M11 -> 301.2
B19: SG&A | C19: ='1. Raw Data - Bloomberg'!D13 -> 1424.6 | D19: ='1. Raw Data - Bloomberg'!E13 -> 1657.5 | E19: ='1. Raw Data - Bloomberg'!F13 -> 1691 | F19: ='1. Raw Data - Bloomberg'!G13 -> 1968.5 | G19: ='1. Raw Data - Bloomberg'!H13 -> 2029 | H19: ='1. Raw Data - Bloomberg'!I13 -> 1922.2 | I19: ='1. Raw Data - Bloomberg'!J13 -> 2215.5 | J19: ='1. Raw Data - Bloomberg'!K13 -> 2448.7 | ... L19: ='1. Raw Data - Bloomberg'!M13 -> 2523.3 | M19: =L19*(1+'3. Historical & Forecast Ratio '!M17) -> 2703.7752 | N19: =M19*(1+'3. Historical & Forecast Ratio '!N17) -> 2897.1586 | O19: =N19*(1+'3. Historical & Forecast Ratio '!O17) -> 3104.3735 | P19: =O19*(1+'3. Historical & Forecast Ratio '!P17) -> 3326.4091 | Q19: =P19*(1+'3. Historical & Forecast Ratio '!Q17) -> 3564.3254 | R19: =Q19*(1+'3. Historical & Forecast Ratio '!R17) -> 3819.2583 | S19: =R19*(1+'3. Historical & Forecast Ratio '!S17) -> 4092.425 | T19: =S19*(1+'3. Historical & Forecast Ratio '!T17) -> 4385.1295 | ... AB19: =AA19*(1+'3. Historical & Forecast Ratio '!AB17) -> 7620.7191
B20: Depreciation & Amortization | C20: ='1. Raw Data - Bloomberg'!D17 -> 893.9 | D20: ='1. Raw Data - Bloomberg'!E17 -> 980.8 | E20: ='1. Raw Data - Bloomberg'!F17 -> 1011.4 | F20: ='1. Raw Data - Bloomberg'!G17 -> 1247 | G20: ='1. Raw Data - Bloomberg'!H17 -> 1377.3 | H20: ='1. Raw Data - Bloomberg'!I17 -> 1431.3 | I20: ='1. Raw Data - Bloomberg'!J17 -> 1441.7 | J20: ='1. Raw Data - Bloomberg'!K17 -> 1447.9 | ... L20: ='1. Raw Data - Bloomberg'!M17 -> 1512.6 | M20: =L20*(1+'3. Historical & Forecast Ratio '!M18) -> 1608.0271 | N20: =M20*(1+'3. Historical & Forecast Ratio '!N18) -> 1709.4745 | O20: =N20*(1+'3. Historical & Forecast Ratio '!O18) -> 1817.3221 | P20: =O20*(1+'3. Historical & Forecast Ratio '!P18) -> 1931.9735 | Q20: =P20*(1+'3. Historical & Forecast Ratio '!Q18) -> 2053.8581 | R20: =Q20*(1+'3. Historical & Forecast Ratio '!R18) -> 2183.4322 | S20: =R20*(1+'3. Historical & Forecast Ratio '!S18) -> 2321.1809 | T20: =S20*(1+'3. Historical & Forecast Ratio '!T18) -> 2467.6198 | ... AB20: =AA20*(1+'3. Historical & Forecast Ratio '!AB18) -> 4025.6166
B21: Other Operating Expenses | C21: ='1. Raw Data - Bloomberg'!D18 -> -10 | D21: ='1. Raw Data - Bloomberg'!E18 -> 250.6 | E21: ='1. Raw Data - Bloomberg'!F18 -> 172.4 | F21: ='1. Raw Data - Bloomberg'!G18 -> -92.7 | G21: ='1. Raw Data - Bloomberg'!H18 -> -190.7 | H21: ='1. Raw Data - Bloomberg'!I18 -> -105.1 | I21: ='1. Raw Data - Bloomberg'!J18 -> -81.2 | J21: ='1. Raw Data - Bloomberg'!K18 -> -146.4 | ... L21: ='1. Raw Data - Bloomberg'!M18 -> 444.1 | M21: =L21*(1+'3. Historical & Forecast Ratio '!M19) -> -288.30237 | N21: =M21*(1+'3. Historical & Forecast Ratio '!N19) -> 187.16113 | O21: =N21*(1+'3. Historical & Forecast Ratio '!O19) -> -121.50191 | P21: =O21*(1+'3. Historical & Forecast Ratio '!P19) -> 78.877026 | Q21: =P21*(1+'3. Historical & Forecast Ratio '!Q19) -> -51.20566 | R21: =Q21*(1+'3. Historical & Forecast Ratio '!R19) -> 33.241867 | S21: =R21*(1+'3. Historical & Forecast Ratio '!S19) -> -21.58007 | T21: =S21*(1+'3. Historical & Forecast Ratio '!T19) -> 14.009424 | ... AB21: =AA21*(1+'3. Historical & Forecast Ratio '!AB19) -> 0.44193641
B22: Total Operating Expenses | C22: =C19+C21+C20 -> 2308.5 | D22: =D19+D21+D20 -> 2888.9 | E22: =E19+E21+E20 -> 2874.8 | F22: =F19+F21+F20 -> 3122.8 | G22: =G19+G21+G20 -> 3215.6 | H22: =H19+H21+H20 -> 3248.4 | I22: =I19+I21+I20 -> 3576 | J22: =J19+J21+J20 -> 3750.2 | ... AB22: =AB19+AB21+AB20 -> 11646.778
B24: EBIT | C24: =C15+C17-C22 -> 3655.6 | D24: =D15+D17-D22 -> 4171.9 | E24: =E15+E17-E22 -> 4351.2 | F24: =F15+F17-F22 -> 4495 | G24: =G15+G17-G22 -> 4570.5 | H24: =H15+H17-H22 -> 2133.2 | I24: =I15+I17-I22 -> 5217.9 | J24: =J15+J17-J22 -> 4855 | ... L24: =L15+L17-L22 -> 5530.3 | M24: =M15-M22 -> 6996.5151 | N24: =N15-N22 -> 7126.6158 | O24: =O15-O22 -> 8099.801 | P24: =P15-P22 -> 8628.5655 | Q24: =Q15-Q22 -> 9558.622 | R24: =R15-R22 -> 10351.788 | S24: =S15-S22 -> 11369.329 | T24: =T15-T22 -> 12389.753 | ... AB24: =AB15-AB22 -> 25494.128
B26: Interest Income | C26: ='1. Raw Data - Bloomberg'!D23 -> 0 | D26: ='1. Raw Data - Bloomberg'!E23 -> 0 | E26: ='1. Raw Data - Bloomberg'!F23 -> 0 | F26: ='1. Raw Data - Bloomberg'!G23 -> 0 | G26: ='1. Raw Data - Bloomberg'!H23 -> 0 | H26: ='1. Raw Data - Bloomberg'!I23 -> 0 | I26: ='1. Raw Data - Bloomberg'!J23 -> 0 | J26: ='1. Raw Data - Bloomberg'!K23 -> 0 | ... L26: ='1. Raw Data - Bloomberg'!M23 -> 0 | M26: =AVERAGE($C26:$L26) -> 0 | N26: =AVERAGE($C26:$L26) -> 0 | O26: =AVERAGE($C26:$L26) -> 0 | P26: =AVERAGE($C26:$L26) -> 0 | Q26: =AVERAGE($C26:$L26) -> 0 | R26: =AVERAGE($C26:$L26) -> 0 | S26: =AVERAGE($C26:$L26) -> 0 | T26: =AVERAGE($C26:$L26) -> 0 | ... AB26: =AVERAGE($C26:$L26) -> 0
B27: Interest Expense | C27: ='1. Raw Data - Bloomberg'!D22 -> 70.5 | D27: ='1. Raw Data - Bloomberg'!E22 -> 81.3 | E27: ='1. Raw Data - Bloomberg'!F22 -> 92.5 | F27: ='1. Raw Data - Bloomberg'!G22 -> 170.3 | G27: ='1. Raw Data - Bloomberg'!H22 -> 331 | H27: ='1. Raw Data - Bloomberg'!I22 -> 437 | I27: ='1. Raw Data - Bloomberg'!J22 -> 469.8 | J27: ='1. Raw Data - Bloomberg'!K22 -> 482.9 | ... L27: ='1. Raw Data - Bloomberg'!M22 -> 562 | M27: =AVERAGE($C27:$L27) -> 324.74 | N27: =AVERAGE($C27:$L27) -> 324.74 | O27: =AVERAGE($C27:$L27) -> 324.74 | P27: =AVERAGE($C27:$L27) -> 324.74 | Q27: =AVERAGE($C27:$L27) -> 324.74 | R27: =AVERAGE($C27:$L27) -> 324.74 | S27: =AVERAGE($C27:$L27) -> 324.74 | T27: =AVERAGE($C27:$L27) -> 324.74 | ... AB27: =AVERAGE($C27:$L27) -> 324.74
B28: Net Interest Expense | C28: =C27-C26 -> 70.5 | D28: =D27-D26 -> 81.3 | E28: =E27-E26 -> 92.5 | F28: =F27-F26 -> 170.3 | G28: =G27-G26 -> 331 | H28: =H27-H26 -> 437 | I28: =I27-I26 -> 469.8 | J28: =J27-J26 -> 482.9 | ... AB28: =AB27-AB26 -> 324.74
B29: Other Non-Op (Income) Loss | C29: ='1. Raw Data - Bloomberg'!D25 -> -43 | D29: ='1. Raw Data - Bloomberg'!E25 -> -102.6 | E29: ='1. Raw Data - Bloomberg'!F25 -> -181.8 | F29: ='1. Raw Data - Bloomberg'!G25 -> -191.4 | G29: ='1. Raw Data - Bloomberg'!H25 -> -96.5 | H29: ='1. Raw Data - Bloomberg'!I25 -> -39.7 | I29: ='1. Raw Data - Bloomberg'!J25 -> -90.1 | J29: ='1. Raw Data - Bloomberg'!K25 -> -97 | ... L29: ='1. Raw Data - Bloomberg'!M25 -> -122.8 | M29: =AVERAGE($C29:$L29) -> -104.61 | N29: =AVERAGE($C29:$L29) -> -104.61 | O29: =AVERAGE($C29:$L29) -> -104.61 | P29: =AVERAGE($C29:$L29) -> -104.61 | Q29: =AVERAGE($C29:$L29) -> -104.61 | R29: =AVERAGE($C29:$L29) -> -104.61 | S29: =AVERAGE($C29:$L29) -> -104.61 | T29: =AVERAGE($C29:$L29) -> -104.61 | ... AB29: =AVERAGE($C29:$L29) -> -104.61
B31: Non-Operating (Income) Loss | C31: =SUM(C28:C29) -> 27.5 | D31: =SUM(D28:D29) -> -21.3 | E31: =SUM(E28:E29) -> -89.3 | F31: =SUM(F28:F29) -> -21.1 | G31: =SUM(G28:G29) -> 234.5 | H31: =SUM(H28:H29) -> 397.3 | I31: =SUM(I28:I29) -> 379.7 | J31: =SUM(J28:J29) -> 385.9 | ... AB31: =SUM(AB28:AB29) -> 220.13
B33: EBT | C33: =C24-C31 -> 3628.1 | D33: =D24-D31 -> 4193.2 | E33: =E24-E31 -> 4440.5 | F33: =F24-F31 -> 4516.1 | G33: =G24-G31 -> 4336 | H33: =H24-H31 -> 1735.9 | I33: =I24-I31 -> 4838.2 | J33: =J24-J31 -> 4469.1 | ... L33: =L24-L31 -> 5091.1 | M33: =M24-M28 -> 6671.7751 | N33: =N24-N28 -> 6801.8758 | O33: =O24-O28 -> 7775.061 | P33: =P24-P28 -> 8303.8255 | Q33: =Q24-Q28 -> 9233.882 | R33: =R24-R28 -> 10027.048 | S33: =S24-S28 -> 11044.589 | T33: =T24-T28 -> 12065.013 | ... AB33: =AB24-AB28 -> 25169.388
B35: Abnormal Loss/Gains | C35: ='1. Raw Data - Bloomberg'!D27 -> -274.9 | D35: ='1. Raw Data - Bloomberg'!E27 -> -5.4 | E35: ='1. Raw Data - Bloomberg'!F27 -> 123 | F35: ='1. Raw Data - Bloomberg'!G27 -> -1263.9 | G35: ='1. Raw Data - Bloomberg'!H27 -> -130.2 | H35: ='1. Raw Data - Bloomberg'!I27 -> 571.5 | I35: ='1. Raw Data - Bloomberg'!J27 -> -518.7 | J35: ='1. Raw Data - Bloomberg'!K27 -> 237.2 | ... L35: ='1. Raw Data - Bloomberg'!M27 -> 121.5 | M35: =AVERAGE($C35:$L35) -> -120.93 | N35: =AVERAGE($C35:$L35) -> -120.93 | O35: =AVERAGE($C35:$L35) -> -120.93 | P35: =AVERAGE($C35:$L35) -> -120.93 | Q35: =AVERAGE($C35:$L35) -> -120.93 | R35: =AVERAGE($C35:$L35) -> -120.93 | S35: =AVERAGE($C35:$L35) -> -120.93 | T35: =AVERAGE($C35:$L35) -> -120.93 | ... AB35: =AVERAGE($C35:$L35) -> -120.93
B37: Adj EBT | C37: =C33-C35 -> 3903 | D37: =D33-D35 -> 4198.6 | E37: =E33-E35 -> 4317.5 | F37: =F33-F35 -> 5780 | G37: =G33-G35 -> 4466.2 | H37: =H33-H35 -> 1164.4 | I37: =I33-I35 -> 5356.9 | J37: =J33-J35 -> 4231.9 | ... AB37: =AB33-AB35 -> 25290.318
B39: Income Tax Expense / Benefit | C39: ='1. Raw Data - Bloomberg'!D38 -> 1143.7 | D39: ='1. Raw Data - Bloomberg'!E38 -> 1379.7 | E39: ='1. Raw Data - Bloomberg'!F38 -> 1432.6 | F39: ='1. Raw Data - Bloomberg'!G38 -> 1262 | G39: ='1. Raw Data - Bloomberg'!H38 -> 871.6 | H39: ='1. Raw Data - Bloomberg'!I38 -> 239.7 | I39: ='1. Raw Data - Bloomberg'!J38 -> 1156.6 | J39: ='1. Raw Data - Bloomberg'!K38 -> 948.5 | ... L39: ='1. Raw Data - Bloomberg'!M38 -> 1207.3 | M39: =M37*'3. Historical & Forecast Ratio '!M22 -> 1493.1945 | N39: =N37*'3. Historical & Forecast Ratio '!N22 -> 1521.7937 | O39: =O37*'3. Historical & Forecast Ratio '!O22 -> 1735.7224 | P39: =P37*'3. Historical & Forecast Ratio '!P22 -> 1851.9571 | Q39: =Q37*'3. Historical & Forecast Ratio '!Q22 -> 2056.4052 | R39: =R37*'3. Historical & Forecast Ratio '!R22 -> 2230.7614 | S39: =S37*'3. Historical & Forecast Ratio '!S22 -> 2454.4406 | T39: =T37*'3. Historical & Forecast Ratio '!T22 -> 2678.7537 | ... AB39: =AB37*'3. Historical & Forecast Ratio '!AB22 -> 5559.3999
B41: Net Profit | C41: =C37-C39 -> 2759.3 | D41: =D37-D39 -> 2818.9 | E41: =E37-E39 -> 2884.9 | F41: =F37-F39 -> 4518 | G41: =G37-G39 -> 3594.6 | H41: =H37-H39 -> 924.7 | I41: =I37-I39 -> 4200.3 | J41: =J37-J39 -> 3283.4 | ... AB41: =AB37-AB39 -> 19730.918
B43: Minority Interest | C43: ='1. Raw Data - Bloomberg'!D46 -> 1.9 | D43: ='1. Raw Data - Bloomberg'!E46 -> 1.2 | E43: ='1. Raw Data - Bloomberg'!F46 -> 0.2 | F43: ='1. Raw Data - Bloomberg'!G46 -> -0.3 | G43: ='1. Raw Data - Bloomberg'!H46 -> -4.6 | H43: ='1. Raw Data - Bloomberg'!I46 -> -3.6 | I43: ='1. Raw Data - Bloomberg'!J46 -> 1 | J43: ='1. Raw Data - Bloomberg'!K46 -> 1.8 | ... L43: ='1. Raw Data - Bloomberg'!M46 -> 1.4 | M43: =AVERAGE($C43:$L43) -> -0.08 | N43: =AVERAGE($C43:$L43) -> -0.08 | O43: =AVERAGE($C43:$L43) -> -0.08 | P43: =AVERAGE($C43:$L43) -> -0.08 | Q43: =AVERAGE($C43:$L43) -> -0.08 | R43: =AVERAGE($C43:$L43) -> -0.08 | S43: =AVERAGE($C43:$L43) -> -0.08 | T43: =AVERAGE($C43:$L43) -> -0.08 | ... AB43: =AVERAGE($C43:$L43) -> -0.08
B45: Net Income, GAAP | C45: =C41-C43 -> 2757.4 | D45: =D41-D43 -> 2817.7 | E45: =E41-E43 -> 2884.7 | F45: =F41-F43 -> 4518.3 | G45: =G41-G43 -> 3599.2 | H45: =H41-H43 -> 928.3 | I45: =I41-I43 -> 4199.3 | J45: =J41-J43 -> 3281.6 | ... AB45: =AB41-AB43 -> 19730.998
B47: Interest Tax Shield | C47: =C28*'3. Historical & Forecast Ratio '!C22 -> 20.658686 | D47: =D28*'3. Historical & Forecast Ratio '!D22 -> 26.715955 | E47: =E28*'3. Historical & Forecast Ratio '!E22 -> 30.692646 | F47: =F28*'3. Historical & Forecast Ratio '!F22 -> 37.183149 | G47: =G28*'3. Historical & Forecast Ratio '!G22 -> 64.596212 | H47: =H28*'3. Historical & Forecast Ratio '!H22 -> 89.95955 | I47: =I28*'3. Historical & Forecast Ratio '!I22 -> 101.43379 | J47: =J28*'3. Historical & Forecast Ratio '!J22 -> 108.23286 | ... AB47: =AB28*'3. Historical & Forecast Ratio '!AB22 -> 71.385403
B48: Operating Taxes | C48: =C39+C47 -> 1164.3587 | D48: =D39+D47 -> 1406.416 | E48: =E39+E47 -> 1463.2926 | F48: =F39+F47 -> 1299.1831 | G48: =G39+G47 -> 936.19621 | H48: =H39+H47 -> 329.65955 | I48: =I39+I47 -> 1258.0338 | J48: =J39+J47 -> 1056.7329 | ... AB48: =AB39+AB47 -> 5630.7853
B50: NOPLAT | C50: =C24+C48 -> 4819.9587 | D50: =D24+D48 -> 5578.316 | E50: =E24+E48 -> 5814.4926 | F50: =F24+F48 -> 5794.1831 | G50: =G24+G48 -> 5506.6962 | H50: =H24+H48 -> 2462.8595 | I50: =I24+I48 -> 6475.9338 | J50: =J24+J48 -> 5911.7329 | ... AB50: =AB24+AB48 -> 31124.913
B52: BALANCE SHEET
B53: PARTICULARS | C53: ACTUALS | M53: NEAR TERM FORECAST | R53: FAR TERM FORECAST | AB53: CV
C54: =2015 -> 2015 | D54: =C54+1 -> 2016 | E54: =D54+1 -> 2017 | F54: =E54+1 -> 2018 | G54: =F54+1 -> 2019 | H54: =G54+1 -> 2020 | I54: =H54+1 -> 2021 | J54: =I54+1 -> 2022 | K54: =J54+1 -> 2023 | ... BV54: =BU54+1 -> 2086
C55: ="FY "&C54 -> FY 2015 | D55: ="FY "&D54 -> FY 2016 | E55: ="FY "&E54 -> FY 2017 | F55: ="FY "&F54 -> FY 2018 | G55: ="FY "&G54 -> FY 2019 | H55: ="FY "&H54 -> FY 2020 | I55: ="FY "&I54 -> FY 2021 | J55: ="FY "&J54 -> FY 2022 | ... AA55: ="FY "&AA54 -> FY 2039 | AB55: Perpetuity
B56: ASSETS:
B57: Operating Current Assets | C57: ='1. Raw Data - Bloomberg'!D104 -> 3971 | D57: ='1. Raw Data - Bloomberg'!E104 -> 4760.5 | E57: ='1. Raw Data - Bloomberg'!F104 -> 5283.4 | F57: ='1. Raw Data - Bloomberg'!G104 -> 12494.2 | G57: ='1. Raw Data - Bloomberg'!H104 -> 5653.9 | H57: ='1. Raw Data - Bloomberg'!I104 -> 7806.4 | I57: ='1. Raw Data - Bloomberg'!J104 -> 9756.4 | J57: ='1. Raw Data - Bloomberg'!K104 -> 7018.7 | ... L57: ='1. Raw Data - Bloomberg'!M104 -> 6847.4
B58: Operating Current Liabilities | C58: ='1. Raw Data - Bloomberg'!D137 -> 3648.1 | D58: ='1. Raw Data - Bloomberg'!E137 -> 4546.9 | E58: ='1. Raw Data - Bloomberg'!F137 -> 4220.7 | F58: ='1. Raw Data - Bloomberg'!G137 -> 5684.2 | G58: ='1. Raw Data - Bloomberg'!H137 -> 6168.7 | H58: ='1. Raw Data - Bloomberg'!I137 -> 7346.8 | I58: ='1. Raw Data - Bloomberg'!J137 -> 8151.4 | J58: ='1. Raw Data - Bloomberg'!K137 -> 9151.8 | ... L58: ='1. Raw Data - Bloomberg'!M137 -> 9070
B59: Net Operating Working Capital | C59: =C57-C58 -> 322.9 | D59: =D57-D58 -> 213.6 | E59: =E57-E58 -> 1062.7 | F59: =F57-F58 -> 6810 | G59: =G57-G58 -> -514.8 | H59: =H57-H58 -> 459.6 | I59: =I57-I58 -> 1605 | J59: =J57-J58 -> -2133.1 | ... L59: =L57-L58 -> -2222.6 | M59: =M9*'3. Historical & Forecast Ratio '!M29 -> 863.81395 | N59: =N9*'3. Historical & Forecast Ratio '!N29 -> 934.39223 | O59: =O9*'3. Historical & Forecast Ratio '!O29 -> 1011.1779 | P59: =P9*'3. Historical & Forecast Ratio '!P29 -> 1094.724 | Q59: =Q9*'3. Historical & Forecast Ratio '!Q29 -> 1185.634 | R59: =R9*'3. Historical & Forecast Ratio '!R29 -> 1284.5664 | S59: =S9*'3. Historical & Forecast Ratio '!S29 -> 1392.24 | T59: =T9*'3. Historical & Forecast Ratio '!T29 -> 1509.4393 | ... AB59: =AB9*'3. Historical & Forecast Ratio '!AB29 -> 2911.3238
B61: Operating Long Term Assets | C61: ='1. Raw Data - Bloomberg'!D105 -> 4088.3 | D61: ='1. Raw Data - Bloomberg'!E105 -> 4533.8 | E61: ='1. Raw Data - Bloomberg'!F105 -> 4919.5 | F61: ='1. Raw Data - Bloomberg'!G105 -> 5929.1 | G61: ='1. Raw Data - Bloomberg'!H105 -> 6431.7 | H61: ='1. Raw Data - Bloomberg'!I105 -> 14375.5 | I61: ='1. Raw Data - Bloomberg'!J105 -> 14605.5 | J61: ='1. Raw Data - Bloomberg'!K105 -> 14576.1 | ... L61: ='1. Raw Data - Bloomberg'!M105 -> 17951.7
B62: Operating Long Term Liabilities | C62: ='1. Raw Data - Bloomberg'!D140+'1. Raw Data - Bloomberg'!D143 -> 600.9 | D62: ='1. Raw Data - Bloomberg'!E140+'1. Raw Data - Bloomberg'!E143 -> 689.7 | E62: ='1. Raw Data - Bloomberg'!F140+'1. Raw Data - Bloomberg'!F143 -> 755.3 | F62: ='1. Raw Data - Bloomberg'!G140+'1. Raw Data - Bloomberg'!G143 -> 8206.2 | G62: ='1. Raw Data - Bloomberg'!H140+'1. Raw Data - Bloomberg'!H143 -> 8114.9 | H62: ='1. Raw Data - Bloomberg'!I140+'1. Raw Data - Bloomberg'!I143 -> 15167.5 | I62: ='1. Raw Data - Bloomberg'!J140+'1. Raw Data - Bloomberg'!J143 -> 14938.8 | J62: ='1. Raw Data - Bloomberg'!K140+'1. Raw Data - Bloomberg'!K143 -> 14405.4 | ... L62: ='1. Raw Data - Bloomberg'!M140+'1. Raw Data - Bloomberg'!M143 -> 15391.4
B63: Net Operating Long Term Assets | C63: =C61-C62 -> 3487.4 | D63: =D61-D62 -> 3844.1 | E63: =E61-E62 -> 4164.2 | F63: =F61-F62 -> -2277.1 | G63: =G61-G62 -> -1683.2 | H63: =H61-H62 -> -792 | I63: =I61-I62 -> -333.3 | J63: =J61-J62 -> 170.7 | ... L63: =L61-L62 -> 2560.3 | M63: =M9*'3. Historical & Forecast Ratio '!M30 -> 1793.9625 | N63: =N9*'3. Historical & Forecast Ratio '!N30 -> 1940.539 | O63: =O9*'3. Historical & Forecast Ratio '!O30 -> 2100.0068 | P63: =P9*'3. Historical & Forecast Ratio '!P30 -> 2273.5147 | Q63: =Q9*'3. Historical & Forecast Ratio '!Q30 -> 2462.3159 | R63: =R9*'3. Historical & Forecast Ratio '!R30 -> 2667.7781 | S63: =S9*'3. Historical & Forecast Ratio '!S30 -> 2891.3939 | T63: =T9*'3. Historical & Forecast Ratio '!T30 -> 3134.7925 | ... AB63: =AB9*'3. Historical & Forecast Ratio '!AB30 -> 6046.216
B65: Intangible Assets | C65: ='1. Raw Data - Bloomberg'!D111 -> 2095.8 | D65: ='1. Raw Data - Bloomberg'!E111 -> 2235.9 | E65: ='1. Raw Data - Bloomberg'!F111 -> 1980.6 | F65: ='1. Raw Data - Bloomberg'!G111 -> 4583.8 | G65: ='1. Raw Data - Bloomberg'!H111 -> 4272.6 | H65: ='1. Raw Data - Bloomberg'!I111 -> 4149.3 | I65: ='1. Raw Data - Bloomberg'!J111 -> 4027.2 | J65: ='1. Raw Data - Bloomberg'!K111 -> 3439.4 | ... L65: ='1. Raw Data - Bloomberg'!M111 -> 3416.6 | M65: =M9*'3. Historical & Forecast Ratio '!M31 -> 4921.5164 | N65: =N9*'3. Historical & Forecast Ratio '!N31 -> 5323.631 | O65: =O9*'3. Historical & Forecast Ratio '!O31 -> 5761.1116 | P65: =P9*'3. Historical & Forecast Ratio '!P31 -> 6237.1093 | Q65: =Q9*'3. Historical & Forecast Ratio '!Q31 -> 6755.0623 | R65: =R9*'3. Historical & Forecast Ratio '!R31 -> 7318.7227 | S65: =S9*'3. Historical & Forecast Ratio '!S31 -> 7932.185 | T65: =T9*'3. Historical & Forecast Ratio '!T31 -> 8599.9194 | ... AB65: =AB9*'3. Historical & Forecast Ratio '!AB31 -> 16587.053
B67: Net Operating Assets | C67: =C59+C63+C65 -> 5906.1 | D67: =D59+D63+D65 -> 6293.6 | E67: =E59+E63+E65 -> 7207.5 | F67: =F59+F63+F65 -> 9116.7 | G67: =G59+G63+G65 -> 2074.6 | H67: =H59+H63+H65 -> 3816.9 | I67: =I59+I63+I65 -> 5298.9 | J67: =J59+J63+J65 -> 1477 | ... AB67: =AB59+AB63+AB65 -> 25544.593
B69: Other Long Term Assets | C69: ='1. Raw Data - Bloomberg'!D118-'1. Raw Data - Bloomberg'!D105-'1. Raw Data - Bloomberg'!D111 -> 2261.2 | D69: ='1. Raw Data - Bloomberg'!E118-'1. Raw Data - Bloomberg'!E105-'1. Raw Data - Bloomberg'!E111 -> 2799.3 | E69: ='1. Raw Data - Bloomberg'!F118-'1. Raw Data - Bloomberg'!F105-'1. Raw Data - Bloomberg'!F111 -> 2182.1 | F69: ='1. Raw Data - Bloomberg'!G118-'1. Raw Data - Bloomberg'!G105-'1. Raw Data - Bloomberg'!G111 -> 1149.3 | G69: ='1. Raw Data - Bloomberg'!H118-'1. Raw Data - Bloomberg'!H105-'1. Raw Data - Bloomberg'!H111 -> 2861.4 | H69: ='1. Raw Data - Bloomberg'!I118-'1. Raw Data - Bloomberg'!I105-'1. Raw Data - Bloomberg'!I111 -> 3043.3 | I69: ='1. Raw Data - Bloomberg'!J118-'1. Raw Data - Bloomberg'!J105-'1. Raw Data - Bloomberg'!J111 -> 3003.5 | J69: ='1. Raw Data - Bloomberg'!K118-'1. Raw Data - Bloomberg'!K105-'1. Raw Data - Bloomberg'!K111 -> 2944.2 | ... L69: ='1. Raw Data - Bloomberg'!M118-'1. Raw Data - Bloomberg'!M105-'1. Raw Data - Bloomberg'!M111 -> 3123.6 | M69: =M9*'3. Historical & Forecast Ratio '!M32 -> 3892.2847 | N69: =N9*'3. Historical & Forecast Ratio '!N32 -> 4210.3055 | O69: =O9*'3. Historical & Forecast Ratio '!O32 -> 4556.2961 | P69: =P9*'3. Historical & Forecast Ratio '!P32 -> 4932.7489 | Q69: =Q9*'3. Historical & Forecast Ratio '!Q32 -> 5342.383 | R69: =R9*'3. Historical & Forecast Ratio '!R32 -> 5788.1656 | S69: =S9*'3. Historical & Forecast Ratio '!S32 -> 6273.3352 | T69: =T9*'3. Historical & Forecast Ratio '!T32 -> 6801.427 | ... AB69: =AB9*'3. Historical & Forecast Ratio '!AB32 -> 13118.22
B70: Excess Cash (plug) | C70: =C95-(C67+C69) -> 600.9 | D70: =D95-(D67+D69) -> 689.7 | E70: =E95-(E67+E69) -> 755.3 | F70: =F95-(F67+F69) -> 8206.2 | G70: =G95-(G67+G69) -> 8114.9 | H70: =H95-(H67+H69) -> 15167.5 | I70: =I95-(I67+I69) -> 14938.8 | J70: =J95-(J67+J69) -> 14405.4 | ... AB70: =AB95-(AB67+AB69) -> 57169.052
B72: Total Assets | C72: =C67+C69+C70 -> 8768.2 | D72: =D67+D69+D70 -> 9782.6 | E72: =E67+E69+E70 -> 10144.9 | F72: =F67+F69+F70 -> 18472.2 | G72: =G67+G69+G70 -> 13050.9 | H72: =H67+H69+H70 -> 22027.7 | I72: =I67+I69+I70 -> 23241.2 | J72: =J67+J69+J70 -> 18826.6 | ... AB72: =AB67+AB69+AB70 -> 95831.865
B74: LIABILITIES & EQUITY
B75: Reconcile Retained Earnings
B76: Beginning Retained Earnings | C76: 5206.6 | D76: =C81 -> 5974.8 | E76: =D81 -> 5949.8 | F76: =E81 -> 5563.2 | G76: =F81 -> 1457.4 | H76: =G81 -> -5771.2 | I76: =H81 -> -7815.6 | J76: =I81 -> -6315.7 | K76: =J81 -> -8449.8 | ... AB76: =AA81 -> 48014.485
B77: Add: Net Profit | C77: ='2. Integrated Finance'!C45 -> 2757.4 | D77: ='2. Integrated Finance'!D45 -> 2817.7 | E77: ='2. Integrated Finance'!E45 -> 2884.7 | F77: ='2. Integrated Finance'!F45 -> 4518.3 | G77: ='2. Integrated Finance'!G45 -> 3599.2 | H77: ='2. Integrated Finance'!H45 -> 928.3 | I77: ='2. Integrated Finance'!I45 -> 4199.3 | J77: ='2. Integrated Finance'!J45 -> 3281.6 | ... L77: ='2. Integrated Finance'!L45 -> 3760.9 | M77: ='2. Integrated Finance'!M41 -> 5299.5106 | N77: ='2. Integrated Finance'!N41 -> 5401.0121 | O77: ='2. Integrated Finance'!O41 -> 6160.2686 | P77: ='2. Integrated Finance'!P41 -> 6572.7983 | Q77: ='2. Integrated Finance'!Q41 -> 7298.4068 | R77: ='2. Integrated Finance'!R41 -> 7917.2162 | S77: ='2. Integrated Finance'!S41 -> 8711.0781 | T77: ='2. Integrated Finance'!T41 -> 9507.1897 | ... AB77: ='2. Integrated Finance'!AB41 -> 19730.918
B78: Less: Dividends | C78: -1016.2 | D78: -1246.2 | E78: -1515.9 | F78: -1760.5 | G78: -1801.6 | H78: -1436.6 | I78: -2697.2 | J78: -2293.5 | K78: -2474.6 | L78: -2625 | M78: =-M77*'3. Historical & Forecast Ratio '!M35 -> -3398.6835 | N78: =-N77*'3. Historical & Forecast Ratio '!N35 -> -3463.7785 | O78: =-O77*'3. Historical & Forecast Ratio '!O35 -> -3950.7051 | P78: =-P77*'3. Historical & Forecast Ratio '!P35 -> -4215.2687 | Q78: =-Q77*'3. Historical & Forecast Ratio '!Q35 -> -4680.6162 | R78: =-R77*'3. Historical & Forecast Ratio '!R35 -> -5077.4711 | S78: =-S77*'3. Historical & Forecast Ratio '!S35 -> -5586.5909 | T78: =-T77*'3. Historical & Forecast Ratio '!T35 -> -6097.1534 | ... AB78: =-AB77*'3. Historical & Forecast Ratio '!AB35 -> -12653.837
B79: Less: Repurchase of stock | C79: -973 | D79: -1596.5 | E79: -1755.4 | F79: -6863.6 | G79: -9521.8 | H79: -1548.6 | I79: 0 | J79: -3122.2 | K79: -455.9 | L79: -1223.9 | M79: 0 | N79: 0 | O79: 0 | P79: 0 | Q79: 0 | R79: 0 | S79: 0 | T79: 0 | U79: 0 | V79: 0 | W79: 0 | X79: 0 | Y79: 0 | Z79: 0 | AA79: 0 | AB79: 0 | AC79: As there Repurchase of Equity is a one-off expense and there is no consistent pattern, we have set the forecast at 0.
B80: Add/Less : Effect of adoption of new accounting guidelines | C80: 0 | D80: 0 | E80: 0 | F80: 0 | G80: 495.6 | H80: 12.5 | I80: -2.2 | J80: 0 | K80: 0 | L80: 0 | M80: 0 | N80: 0 | O80: 0 | P80: 0 | Q80: 0 | R80: 0 | S80: 0 | T80: 0 | U80: 0 | V80: 0 | W80: 0 | X80: 0 | Y80: 0 | Z80: 0 | AA80: 0 | AB80: 0 | AC80: As there is no consistent pattern, we have set the forecast at 0.
B81: Closing Retained Earnings | C81: =SUM(C76:C80) -> 5974.8 | D81: =SUM(D76:D80) -> 5949.8 | E81: =SUM(E76:E80) -> 5563.2 | F81: =SUM(F76:F80) -> 1457.4 | G81: =SUM(G76:G80) -> -5771.2 | H81: =SUM(H76:H80) -> -7815.6 | I81: =SUM(I76:I80) -> -6315.7 | J81: =SUM(J76:J80) -> -8449.8 | ... AB81: =SUM(AB76:AB80) -> 55091.566
B83: Liabilities
B84: Long Term Debt | C84: ='1. Raw Data - Bloomberg'!D138 -> 2347.5 | D84: ='1. Raw Data - Bloomberg'!E138 -> 3202.2 | E84: ='1. Raw Data - Bloomberg'!F138 -> 3932.6 | F84: ='1. Raw Data - Bloomberg'!G138 -> 9090.2 | G84: ='1. Raw Data - Bloomberg'!H138 -> 11167 | H84: ='1. Raw Data - Bloomberg'!I138 -> 22321.3 | I84: ='1. Raw Data - Bloomberg'!J138 -> 21354.9 | J84: ='1. Raw Data - Bloomberg'!K138 -> 20635.1 | ... L84: ='1. Raw Data - Bloomberg'!M138 -> 23091.1 | M84: =L84*(1+'3. Historical & Forecast Ratio '!M34) -> 24014.744 | N84: =M84*(1+'3. Historical & Forecast Ratio '!N34) -> 24975.334 | O84: =N84*(1+'3. Historical & Forecast Ratio '!O34) -> 25724.594 | P84: =O84*(1+'3. Historical & Forecast Ratio '!P34) -> 26496.332 | Q84: =P84*(1+'3. Historical & Forecast Ratio '!Q34) -> 27291.222 | R84: =Q84*(1+'3. Historical & Forecast Ratio '!R34) -> 28109.958 | S84: =R84*(1+'3. Historical & Forecast Ratio '!S34) -> 28672.157 | T84: =S84*(1+'3. Historical & Forecast Ratio '!T34) -> 29245.6 | ... AB84: =AA84*(1+'3. Historical & Forecast Ratio '!AB34) -> 34265.882
B85: Other Long Term Liabilities | C85: ='1. Raw Data - Bloomberg'!D143 -> 600.9 | D85: ='1. Raw Data - Bloomberg'!E143 -> 689.7 | E85: ='1. Raw Data - Bloomberg'!F143 -> 755.3 | F85: ='1. Raw Data - Bloomberg'!G143 -> 8206.2 | G85: ='1. Raw Data - Bloomberg'!H143 -> 8114.9 | H85: ='1. Raw Data - Bloomberg'!I143 -> 7505.8 | I85: ='1. Raw Data - Bloomberg'!J143 -> 7200.8 | J85: ='1. Raw Data - Bloomberg'!K143 -> 6890.2 | ... L85: ='1. Raw Data - Bloomberg'!M143 -> 6619.8 | M85: =AVERAGE(C85:L85) -> 5319.92 | N85: =AVERAGE(D85:M85) -> 5791.822 | O85: =AVERAGE(E85:N85) -> 6302.0342 | P85: =AVERAGE(F85:O85) -> 6856.7076 | Q85: =AVERAGE(G85:P85) -> 6721.7584 | R85: =AVERAGE(H85:Q85) -> 6582.4442 | S85: =AVERAGE(I85:R85) -> 6490.1086 | T85: =AVERAGE(J85:S85) -> 6419.0395 | ... AB85: =AVERAGE(R85:AA85) -> 6440.2161
B86: Total Liabilities | C86: =C84+C85 -> 2948.4 | D86: =D84+D85 -> 3891.9 | E86: =E84+E85 -> 4687.9 | F86: =F84+F85 -> 17296.4 | G86: =G84+G85 -> 19281.9 | H86: =H84+H85 -> 29827.1 | I86: =I84+I85 -> 28555.7 | J86: =J84+J85 -> 27525.3 | ... AB86: =AB84+AB85 -> 40706.098
B88: Equity
B89: Issued Equity | C89: ='1. Raw Data - Bloomberg'!D155 -> 42.6 | D89: ='1. Raw Data - Bloomberg'!E155 -> 42.6 | E89: ='1. Raw Data - Bloomberg'!F155 -> 42.5 | F89: ='1. Raw Data - Bloomberg'!G155 -> 42.4 | G89: ='1. Raw Data - Bloomberg'!H155 -> 42.3 | H89: ='1. Raw Data - Bloomberg'!I155 -> 375.1 | I89: ='1. Raw Data - Bloomberg'!J155 -> 847.3 | J89: ='1. Raw Data - Bloomberg'!K155 -> 206.4 | ... L89: ='1. Raw Data - Bloomberg'!M155 -> 323.7 | M89: =L89*(1+'3. Historical & Forecast Ratio '!M36) -> 320.463 | N89: =M89*(1+'3. Historical & Forecast Ratio '!N36) -> 314.05374 | O89: =N89*(1+'3. Historical & Forecast Ratio '!O36) -> 314.05374 | P89: =O89*(1+'3. Historical & Forecast Ratio '!P36) -> 314.05374 | Q89: =P89*(1+'3. Historical & Forecast Ratio '!Q36) -> 314.05374 | R89: =Q89*(1+'3. Historical & Forecast Ratio '!R36) -> 314.05374 | S89: =R89*(1+'3. Historical & Forecast Ratio '!S36) -> 317.19428 | T89: =S89*(1+'3. Historical & Forecast Ratio '!T36) -> 320.36622 | ... AB89: =AA89*(1+'3. Historical & Forecast Ratio '!AB36) -> 346.91071
B90: Other Equity | C90: ='1. Raw Data - Bloomberg'!D160 -> -199.4 | D90: ='1. Raw Data - Bloomberg'!E160 -> -108.4 | E90: ='1. Raw Data - Bloomberg'!F160 -> -155.6 | F90: ='1. Raw Data - Bloomberg'!G160 -> -330.3 | G90: ='1. Raw Data - Bloomberg'!H160 -> -503.3 | H90: ='1. Raw Data - Bloomberg'!I160 -> -364.6 | I90: ='1. Raw Data - Bloomberg'!J160 -> 147.2 | J90: ='1. Raw Data - Bloomberg'!K160 -> -463.2 | ... L90: ='1. Raw Data - Bloomberg'!M160 -> -428.8 | M90: =AVERAGE(C90:L90) -> -318.46 | N90: =M90 -> -318.46 | O90: =N90 -> -318.46 | P90: =O90 -> -318.46 | Q90: =P90 -> -318.46 | R90: =Q90 -> -318.46 | S90: =R90 -> -318.46 | T90: =S90 -> -318.46 | U90: =T90 -> -318.46 | ... AB90: =AA90 -> -318.46
B91: Retained Earnings | C91: =C81 -> 5974.8 | D91: =D81 -> 5949.8 | E91: =E81 -> 5563.2 | F91: =F81 -> 1457.4 | G91: =G81 -> -5771.2 | H91: =H81 -> -7815.6 | I91: =I81 -> -6315.7 | J91: =J81 -> -8449.8 | ... AB91: =AB81 -> 55091.566
B92: Minority Interest | C92: ='1. Raw Data - Bloomberg'!D162 -> 1.8 | D92: ='1. Raw Data - Bloomberg'!E162 -> 6.7 | E92: ='1. Raw Data - Bloomberg'!F162 -> 6.9 | F92: ='1. Raw Data - Bloomberg'!G162 -> 6.3 | G92: ='1. Raw Data - Bloomberg'!H162 -> 1.2 | H92: ='1. Raw Data - Bloomberg'!I162 -> 5.7 | I92: ='1. Raw Data - Bloomberg'!J162 -> 6.7 | J92: ='1. Raw Data - Bloomberg'!K162 -> 7.9 | ... L92: ='1. Raw Data - Bloomberg'!M162 -> 7.3 | M92: =AVERAGE(C92:L92) -> 5.75 | N92: =M92 -> 5.75 | O92: =N92 -> 5.75 | P92: =O92 -> 5.75 | Q92: =P92 -> 5.75 | R92: =Q92 -> 5.75 | S92: =R92 -> 5.75 | T92: =S92 -> 5.75 | U92: =T92 -> 5.75 | ... AB92: =AA92 -> 5.75
B93: Total Equity | C93: =SUM(C89:C92) -> 5819.8 | D93: =SUM(D89:D92) -> 5890.7 | E93: =SUM(E89:E92) -> 5457 | F93: =SUM(F89:F92) -> 1175.8 | G93: =SUM(G89:G92) -> -6231 | H93: =SUM(H89:H92) -> -7799.4 | I93: =SUM(I89:I92) -> -5314.5 | J93: =SUM(J89:J92) -> -8698.7 | ... AB93: =SUM(AB89:AB92) -> 55125.766
B95: Total Liabilities & Equity | C95: =C86+C93 -> 8768.2 | D95: =D86+D93 -> 9782.6 | E95: =E86+E93 -> 10144.9 | F95: =F86+F93 -> 18472.2 | G95: =G86+G93 -> 13050.9 | H95: =H86+H93 -> 22027.7 | I95: =I86+I93 -> 23241.2 | J95: =J86+J93 -> 18826.6 | ... AB95: =AB86+AB93 -> 95831.865

Sheet 3. Historical & Forecast Ratio 
B2: Historical & Forecast Ratio - Starbucks US
B5: INCOME STATEMENT
B6: PARTICULARS | C6: ACTUALS | M6: NEAR TERM FORECAST | R6: FAR TERM FORECAST | AB6: CV
C7: =2015 -> 2015 | D7: =C7+1 -> 2016 | E7: =D7+1 -> 2017 | F7: =E7+1 -> 2018 | G7: =F7+1 -> 2019 | H7: =G7+1 -> 2020 | I7: =H7+1 -> 2021 | J7: =I7+1 -> 2022 | K7: =J7+1 -> 2023 | ... BV7: =BU7+1 -> 2086
C8: ="FY "&C7 -> FY 2015 | D8: ="FY "&D7 -> FY 2016 | E8: ="FY "&E7 -> FY 2017 | F8: ="FY "&F7 -> FY 2018 | G8: ="FY "&G7 -> FY 2019 | H8: ="FY "&H7 -> FY 2020 | I8: ="FY "&I7 -> FY 2021 | J8: ="FY "&J7 -> FY 2022 | ... AA8: ="FY "&AA7 -> FY 2039 | AB8: Perpetuity
B9: Revenue % YoY | D9: =('2. Integrated Finance'!D9-'2. Integrated Finance'!C9)/'2. Integrated Finance'!C9 -> 0.11236412 | E9: =('2. Integrated Finance'!E9-'2. Integrated Finance'!D9)/'2. Integrated Finance'!D9 -> 0.050239493 | F9: =('2. Integrated Finance'!F9-'2. Integrated Finance'!E9)/'2. Integrated Finance'!E9 -> 0.1041998 | G9: =('2. Integrated Finance'!G9-'2. Integrated Finance'!F9)/'2. Integrated Finance'!F9 -> 0.072376059 | H9: =('2. Integrated Finance'!H9-'2. Integrated Finance'!G9)/'2. Integrated Finance'!G9 -> -0.11281622 | I9: =('2. Integrated Finance'!I9-'2. Integrated Finance'!H9)/'2. Integrated Finance'!H9 -> 0.2356748 | J9: =('2. Integrated Finance'!J9-'2. Integrated Finance'!I9)/'2. Integrated Finance'!I9 -> 0.10976029 | K9: =('2. Integrated Finance'!K9-'2. Integrated Finance'!J9)/'2. Integrated Finance'!J9 -> 0.1155121 | L9: =('2. Integrated Finance'!L9-'2. Integrated Finance'!K9)/'2. Integrated Finance'!K9 -> 0.0055760015 | M9: =AVERAGE($C9:$L9) -> 0.076987384 | N9: =AVERAGE($C9:$L9) -> 0.076987384 | O9: =AVERAGE($C9:$L9) -> 0.076987384 | P9: =AVERAGE($C9:$L9) -> 0.076987384 | Q9: =AVERAGE($C9:$L9) -> 0.076987384 | R9: =AVERAGE($C9:$L9) -> 0.076987384 | S9: =AVERAGE($C9:$L9) -> 0.076987384 | T9: =AVERAGE($C9:$L9) -> 0.076987384 | ... AB9: =AVERAGE($C9:$L9) -> 0.076987384
B10: Company Operated Retail % YoY | D10: =('2. Integrated Finance'!D10-'2. Integrated Finance'!C10)/'2. Integrated Finance'!C10 -> 0.10836135 | E10: =('2. Integrated Finance'!E10-'2. Integrated Finance'!D10)/'2. Integrated Finance'!D10 -> 0.047886203 | F10: =('2. Integrated Finance'!F10-'2. Integrated Finance'!E10)/'2. Integrated Finance'!E10 -> 0.11555349 | G10: =('2. Integrated Finance'!G10-'2. Integrated Finance'!F10)/'2. Integrated Finance'!F10 -> 0.094163116 | H10: =('2. Integrated Finance'!H10-'2. Integrated Finance'!G10)/'2. Integrated Finance'!G10 -> -0.11046026 | I10: =('2. Integrated Finance'!I10-'2. Integrated Finance'!H10)/'2. Integrated Finance'!H10 -> 0.28398193 | J10: =('2. Integrated Finance'!J10-'2. Integrated Finance'!I10)/'2. Integrated Finance'!I10 -> 0.080021945 | K10: =('2. Integrated Finance'!K10-'2. Integrated Finance'!J10)/'2. Integrated Finance'!J10 -> 0.10860134 | L10: =('2. Integrated Finance'!L10-'2. Integrated Finance'!K10)/'2. Integrated Finance'!K10 -> 0.010304694 | M10: =AVERAGE($C10:$L10) -> 0.082045979 | N10: =AVERAGE($C10:$L10) -> 0.082045979 | O10: =AVERAGE($C10:$L10) -> 0.082045979 | P10: =AVERAGE($C10:$L10) -> 0.082045979 | Q10: =AVERAGE($C10:$L10) -> 0.082045979 | R10: =AVERAGE($C10:$L10) -> 0.082045979 | S10: =AVERAGE($C10:$L10) -> 0.082045979 | T10: =AVERAGE($C10:$L10) -> 0.082045979 | ... AB10: =AVERAGE($C10:$L10) -> 0.082045979
B11: Licensed Stores % YoY | D11: =('2. Integrated Finance'!D11-'2. Integrated Finance'!C11)/'2. Integrated Finance'!C11 -> 0.15699017 | E11: =('2. Integrated Finance'!E11-'2. Integrated Finance'!D11)/'2. Integrated Finance'!D11 -> 0.093213258 | F11: =('2. Integrated Finance'!F11-'2. Integrated Finance'!E11)/'2. Integrated Finance'!E11 -> 0.12619958 | G11: =('2. Integrated Finance'!G11-'2. Integrated Finance'!F11)/'2. Integrated Finance'!F11 -> 0.084005731 | H11: =('2. Integrated Finance'!H11-'2. Integrated Finance'!G11)/'2. Integrated Finance'!G11 -> -0.19057391 | I11: =('2. Integrated Finance'!I11-'2. Integrated Finance'!H11)/'2. Integrated Finance'!H11 -> 0.15319496 | J11: =('2. Integrated Finance'!J11-'2. Integrated Finance'!I11)/'2. Integrated Finance'!I11 -> 0.36216277 | K11: =('2. Integrated Finance'!K11-'2. Integrated Finance'!J11)/'2. Integrated Finance'!J11 -> 0.23449596 | L11: =('2. Integrated Finance'!L11-'2. Integrated Finance'!K11)/'2. Integrated Finance'!K11 -> -0.0016841359 | M11: =AVERAGE($C$11:$L$11) -> 0.1131116 | N11: =AVERAGE($C$11:$L$11) -> 0.1131116 | O11: =AVERAGE($C$11:$L$11) -> 0.1131116 | P11: =AVERAGE($C$11:$L$11) -> 0.1131116 | Q11: =AVERAGE($C$11:$L$11) -> 0.1131116 | R11: =AVERAGE($C$11:$L$11) -> 0.1131116 | S11: =AVERAGE($C$11:$L$11) -> 0.1131116 | T11: =AVERAGE($C$11:$L$11) -> 0.1131116 | ... AB11: =AVERAGE($C$11:$L$11) -> 0.1131116
B12: CPG, Foodservice and Other % YoY | D12: =('2. Integrated Finance'!D12-'2. Integrated Finance'!C12)/'2. Integrated Finance'!C12 -> 0.10178274 | E12: =('2. Integrated Finance'!E12-'2. Integrated Finance'!D12)/'2. Integrated Finance'!D12 -> 0.027399033 | F12: =('2. Integrated Finance'!F12-'2. Integrated Finance'!E12)/'2. Integrated Finance'!E12 -> -0.0017218932 | G12: =('2. Integrated Finance'!G12-'2. Integrated Finance'!F12)/'2. Integrated Finance'!F12 -> -0.12107699 | H12: =('2. Integrated Finance'!H12-'2. Integrated Finance'!G12)/'2. Integrated Finance'!G12 -> -0.030107218 | I12: =('2. Integrated Finance'!I12-'2. Integrated Finance'!H12)/'2. Integrated Finance'!H12 -> -0.1264867 | J12: =('2. Integrated Finance'!J12-'2. Integrated Finance'!I12)/'2. Integrated Finance'!I12 -> 0.14050847 | K12: =('2. Integrated Finance'!K12-'2. Integrated Finance'!J12)/'2. Integrated Finance'!J12 -> -0.0089661663 | L12: =('2. Integrated Finance'!L12-'2. Integrated Finance'!K12)/'2. Integrated Finance'!K12 -> -0.047685694 | M12: =AVERAGE($C12:$L12) -> -0.0073727121 | N12: =AVERAGE($C12:$L12) -> -0.0073727121 | O12: =AVERAGE($C12:$L12) -> -0.0073727121 | P12: =AVERAGE($C12:$L12) -> -0.0073727121 | Q12: =AVERAGE($C12:$L12) -> -0.0073727121 | R12: =AVERAGE($C12:$L12) -> -0.0073727121 | S12: =AVERAGE($C12:$L12) -> -0.0073727121 | T12: =AVERAGE($C12:$L12) -> -0.0073727121 | ... AB12: =AVERAGE($C12:$L12) -> -0.0073727121
B13: COGS % Revenue | C13: ='2. Integrated Finance'!C13/'2. Integrated Finance'!C9 -> 0.68876515 | D13: ='2. Integrated Finance'!D13/'2. Integrated Finance'!D9 -> 0.68368213 | E13: ='2. Integrated Finance'!E13/'2. Integrated Finance'!E9 -> 0.69470402 | F13: ='2. Integrated Finance'!F13/'2. Integrated Finance'!F9 -> 0.70401505 | G13: ='2. Integrated Finance'!G13/'2. Integrated Finance'!G9 -> 0.71752186 | H13: ='2. Integrated Finance'!H13/'2. Integrated Finance'!H9 -> 0.78488392 | I13: ='2. Integrated Finance'!I13/'2. Integrated Finance'!I9 -> 0.71065291 | J13: ='2. Integrated Finance'!J13/'2. Integrated Finance'!J9 -> 0.74043342 | ... L13: ='2. Integrated Finance'!L13/'2. Integrated Finance'!L9 -> 0.73161637 | M13: =AVERAGE($C13:$L13) -> 0.71825838 | N13: =AVERAGE($C13:$L13) -> 0.71825838 | O13: =AVERAGE($C13:$L13) -> 0.71825838 | P13: =AVERAGE($C13:$L13) -> 0.71825838 | Q13: =AVERAGE($C13:$L13) -> 0.71825838 | R13: =AVERAGE($C13:$L13) -> 0.71825838 | S13: =AVERAGE($C13:$L13) -> 0.71825838 | T13: =AVERAGE($C13:$L13) -> 0.71825838 | ... AB13: =AVERAGE($C13:$L13) -> 0.71825838
B14: Gross Profit Margin | C14: =(1-C13) -> 0.31123485 | D14: =(1-D13) -> 0.31631787 | E14: =(1-E13) -> 0.30529598 | F14: =(1-F13) -> 0.29598495 | G14: =(1-G13) -> 0.28247814 | H14: =(1-H13) -> 0.21511608 | I14: =(1-I13) -> 0.28934709 | J14: =(1-J13) -> 0.25956658 | ... AB14: =(1-AB13) -> 0.28174162
B16: Operating Expenses % YoY | D16: =('2. Integrated Finance'!D22-'2. Integrated Finance'!C22)/'2. Integrated Finance'!C22 -> 0.25141867 | E16: =('2. Integrated Finance'!E22-'2. Integrated Finance'!D22)/'2. Integrated Finance'!D22 -> -0.0048807505 | F16: =('2. Integrated Finance'!F22-'2. Integrated Finance'!E22)/'2. Integrated Finance'!E22 -> 0.086266871 | G16: =('2. Integrated Finance'!G22-'2. Integrated Finance'!F22)/'2. Integrated Finance'!F22 -> 0.029716921 | H16: =('2. Integrated Finance'!H22-'2. Integrated Finance'!G22)/'2. Integrated Finance'!G22 -> 0.010200274 | I16: =('2. Integrated Finance'!I22-'2. Integrated Finance'!H22)/'2. Integrated Finance'!H22 -> 0.10084965 | J16: =('2. Integrated Finance'!J22-'2. Integrated Finance'!I22)/'2. Integrated Finance'!I22 -> 0.048713647 | K16: =('2. Integrated Finance'!K22-'2. Integrated Finance'!J22)/'2. Integrated Finance'!J22 -> 0.1581249 | L16: =('2. Integrated Finance'!L22-'2. Integrated Finance'!K22)/'2. Integrated Finance'!K22 -> 0.031497513 | M16: =AVERAGE($C16:$L16) -> 0.079100855 | N16: =AVERAGE($C16:$L16) -> 0.079100855 | O16: =AVERAGE($C16:$L16) -> 0.079100855 | P16: =AVERAGE($C16:$L16) -> 0.079100855 | Q16: =AVERAGE($C16:$L16) -> 0.079100855 | R16: =AVERAGE($C16:$L16) -> 0.079100855 | S16: =AVERAGE($C16:$L16) -> 0.079100855 | T16: =AVERAGE($C16:$L16) -> 0.079100855 | ... AB16: =AVERAGE($C16:$L16) -> 0.079100855
B17: SG&A % YoY | D17: =('2. Integrated Finance'!D19-'2. Integrated Finance'!C19)/'2. Integrated Finance'!C19 -> 0.16348449 | E17: =('2. Integrated Finance'!E19-'2. Integrated Finance'!D19)/'2. Integrated Finance'!D19 -> 0.020211161 | F17: =('2. Integrated Finance'!F19-'2. Integrated Finance'!E19)/'2. Integrated Finance'!E19 -> 0.16410408 | G17: =('2. Integrated Finance'!G19-'2. Integrated Finance'!F19)/'2. Integrated Finance'!F19 -> 0.030734061 | H17: =('2. Integrated Finance'!H19-'2. Integrated Finance'!G19)/'2. Integrated Finance'!G19 -> -0.052636767 | I17: =('2. Integrated Finance'!I19-'2. Integrated Finance'!H19)/'2. Integrated Finance'!H19 -> 0.15258558 | J17: =('2. Integrated Finance'!J19-'2. Integrated Finance'!I19)/'2. Integrated Finance'!I19 -> 0.10525841 | K17: =('2. Integrated Finance'!K19-'2. Integrated Finance'!J19)/'2. Integrated Finance'!J19 -> 0.20435333 | L17: =('2. Integrated Finance'!L19-'2. Integrated Finance'!K19)/'2. Integrated Finance'!K19 -> -0.14438303 | M17: =AVERAGE($C17:$L17) -> 0.071523479 | N17: =AVERAGE($C17:$L17) -> 0.071523479 | O17: =AVERAGE($C17:$L17) -> 0.071523479 | P17: =AVERAGE($C17:$L17) -> 0.071523479 | Q17: =AVERAGE($C17:$L17) -> 0.071523479 | R17: =AVERAGE($C17:$L17) -> 0.071523479 | S17: =AVERAGE($C17:$L17) -> 0.071523479 | T17: =AVERAGE($C17:$L17) -> 0.071523479 | ... AB17: =AVERAGE($C17:$L17) -> 0.071523479
B18: Depreciation & Amortization % YoY | D18: =('2. Integrated Finance'!D20-'2. Integrated Finance'!C20)/'2. Integrated Finance'!C20 -> 0.097214454 | E18: =('2. Integrated Finance'!E20-'2. Integrated Finance'!D20)/'2. Integrated Finance'!D20 -> 0.031199021 | F18: =('2. Integrated Finance'!F20-'2. Integrated Finance'!E20)/'2. Integrated Finance'!E20 -> 0.23294443 | G18: =('2. Integrated Finance'!G20-'2. Integrated Finance'!F20)/'2. Integrated Finance'!F20 -> 0.10449078 | H18: =('2. Integrated Finance'!H20-'2. Integrated Finance'!G20)/'2. Integrated Finance'!G20 -> 0.039207144 | I18: =('2. Integrated Finance'!I20-'2. Integrated Finance'!H20)/'2. Integrated Finance'!H20 -> 0.0072661217 | J18: =('2. Integrated Finance'!J20-'2. Integrated Finance'!I20)/'2. Integrated Finance'!I20 -> 0.0043004786 | K18: =('2. Integrated Finance'!K20-'2. Integrated Finance'!J20)/'2. Integrated Finance'!J20 -> -0.058912908 | L18: =('2. Integrated Finance'!L20-'2. Integrated Finance'!K20)/'2. Integrated Finance'!K20 -> 0.11008366 | M18: =AVERAGE($C18:$L18) -> 0.063088132 | N18: =AVERAGE($C18:$L18) -> 0.063088132 | O18: =AVERAGE($C18:$L18) -> 0.063088132 | P18: =AVERAGE($C18:$L18) -> 0.063088132 | Q18: =AVERAGE($C18:$L18) -> 0.063088132 | R18: =AVERAGE($C18:$L18) -> 0.063088132 | S18: =AVERAGE($C18:$L18) -> 0.063088132 | T18: =AVERAGE($C18:$L18) -> 0.063088132 | ... AB18: =AVERAGE($C18:$L18) -> 0.063088132
B19: Other Operating Expenses % YoY | D19: =('2. Integrated Finance'!D21-'2. Integrated Finance'!C21)/'2. Integrated Finance'!C21 -> -26.06 | E19: =('2. Integrated Finance'!E21-'2. Integrated Finance'!D21)/'2. Integrated Finance'!D21 -> -0.31205108 | F19: =('2. Integrated Finance'!F21-'2. Integrated Finance'!E21)/'2. Integrated Finance'!E21 -> -1.537703 | G19: =('2. Integrated Finance'!G21-'2. Integrated Finance'!F21)/'2. Integrated Finance'!F21 -> 1.0571737 | H19: =('2. Integrated Finance'!H21-'2. Integrated Finance'!G21)/'2. Integrated Finance'!G21 -> -0.44887257 | I19: =('2. Integrated Finance'!I21-'2. Integrated Finance'!H21)/'2. Integrated Finance'!H21 -> -0.22740247 | J19: =('2. Integrated Finance'!J21-'2. Integrated Finance'!I21)/'2. Integrated Finance'!I21 -> 0.80295567 | K19: =('2. Integrated Finance'!K21-'2. Integrated Finance'!J21)/'2. Integrated Finance'!J21 -> -1.2151639 | L19: =('2. Integrated Finance'!L21-'2. Integrated Finance'!K21)/'2. Integrated Finance'!K21 -> 13.098413 | M19: =AVERAGE($C19:$L19) -> -1.6491834 | N19: =AVERAGE($C19:$L19) -> -1.6491834 | O19: =AVERAGE($C19:$L19) -> -1.6491834 | P19: =AVERAGE($C19:$L19) -> -1.6491834 | Q19: =AVERAGE($C19:$L19) -> -1.6491834 | R19: =AVERAGE($C19:$L19) -> -1.6491834 | S19: =AVERAGE($C19:$L19) -> -1.6491834 | T19: =AVERAGE($C19:$L19) -> -1.6491834 | ... AB19: =AVERAGE($C19:$L19) -> -1.6491834
B20: EBITA Margin | C20: ='2. Integrated Finance'!C24/'2. Integrated Finance'!C9 -> 0.19076644 | D20: ='2. Integrated Finance'!D24/'2. Integrated Finance'!D9 -> 0.19571775 | E20: ='2. Integrated Finance'!E24/'2. Integrated Finance'!E9 -> 0.19436454 | F20: ='2. Integrated Finance'!F24/'2. Integrated Finance'!F9 -> 0.18184025 | G20: ='2. Integrated Finance'!G24/'2. Integrated Finance'!G9 -> 0.17241574 | H20: ='2. Integrated Finance'!H24/'2. Integrated Finance'!H9 -> 0.090704992 | I20: ='2. Integrated Finance'!I24/'2. Integrated Finance'!I9 -> 0.17955238 | J20: ='2. Integrated Finance'!J24/'2. Integrated Finance'!J9 -> 0.15054124 | ... AB20: ='2. Integrated Finance'!AB24/'2. Integrated Finance'!AB9 -> 0.19339208
B22: Effective Tax Rate | C22: ='2. Integrated Finance'!C39/'2. Integrated Finance'!C37 -> 0.293031 | D22: ='2. Integrated Finance'!D39/'2. Integrated Finance'!D37 -> 0.32860954 | E22: ='2. Integrated Finance'!E39/'2. Integrated Finance'!E37 -> 0.33181239 | F22: ='2. Integrated Finance'!F39/'2. Integrated Finance'!F37 -> 0.2183391 | G22: ='2. Integrated Finance'!G39/'2. Integrated Finance'!G37 -> 0.19515472 | H22: ='2. Integrated Finance'!H39/'2. Integrated Finance'!H37 -> 0.20585709 | I22: ='2. Integrated Finance'!I39/'2. Integrated Finance'!I37 -> 0.21590845 | J22: ='2. Integrated Finance'!J39/'2. Integrated Finance'!J37 -> 0.224131 | ... L22: ='2. Integrated Finance'!L39/'2. Integrated Finance'!L37 -> 0.24293706 | M22: =AVERAGE($F$22:$L$22) -> 0.21982325 | N22: =AVERAGE($F$22:$L$22) -> 0.21982325 | O22: =AVERAGE($F$22:$L$22) -> 0.21982325 | P22: =AVERAGE($F$22:$L$22) -> 0.21982325 | Q22: =AVERAGE($F$22:$L$22) -> 0.21982325 | R22: =AVERAGE($F$22:$L$22) -> 0.21982325 | S22: =AVERAGE($F$22:$L$22) -> 0.21982325 | T22: =AVERAGE($F$22:$L$22) -> 0.21982325 | ... AB22: =AVERAGE($F$22:$L$22) -> 0.21982325
B23: Depreciation % Rev | C23: ='5. Re-org Fin Stmts'!C26/'2. Integrated Finance'!C9 -> 0.044038679 | D23: ='5. Re-org Fin Stmts'!D26/'2. Integrated Finance'!D9 -> 0.043324467 | E23: ='5. Re-org Fin Stmts'!E26/'2. Integrated Finance'!E9 -> 0.042609931 | F23: ='5. Re-org Fin Stmts'!F26/'2. Integrated Finance'!F9 -> 0.042901353 | G23: ='5. Re-org Fin Stmts'!G26/'2. Integrated Finance'!G9 -> 0.043174668 | H23: ='5. Re-org Fin Stmts'!H26/'2. Integrated Finance'!H9 -> 0.051347904 | I23: ='5. Re-org Fin Stmts'!I26/'2. Integrated Finance'!I9 -> 0.041922741 | J23: ='5. Re-org Fin Stmts'!J26/'2. Integrated Finance'!J9 -> 0.038920568 | ... L23: ='5. Re-org Fin Stmts'!L26/'2. Integrated Finance'!L9 -> 0.041248113 | M23: =AVERAGE($C23:$L23) -> 0.042676647 | N23: =AVERAGE($C23:$L23) -> 0.042676647 | O23: =AVERAGE($C23:$L23) -> 0.042676647 | P23: =AVERAGE($C23:$L23) -> 0.042676647 | Q23: =AVERAGE($C23:$L23) -> 0.042676647 | R23: =AVERAGE($C23:$L23) -> 0.042676647 | S23: =AVERAGE($C23:$L23) -> 0.042676647 | T23: =AVERAGE($C23:$L23) -> 0.042676647 | ... AB23: =AVERAGE($C23:$L23) -> 0.042676647
B25: BALANCE SHEET
B26: PARTICULARS | C26: ACTUALS | M26: NEAR TERM FORECAST | R26: FAR TERM FORECAST | AB26: CV
C27: =2015 -> 2015 | D27: =C27+1 -> 2016 | E27: =D27+1 -> 2017 | F27: =E27+1 -> 2018 | G27: =F27+1 -> 2019 | H27: =G27+1 -> 2020 | I27: =H27+1 -> 2021 | J27: =I27+1 -> 2022 | K27: =J27+1 -> 2023 | ... BV27: =BU27+1 -> 2086
C28: ="FY "&C27 -> FY 2015 | D28: ="FY "&D27 -> FY 2016 | E28: ="FY "&E27 -> FY 2017 | F28: ="FY "&F27 -> FY 2018 | G28: ="FY "&G27 -> FY 2019 | H28: ="FY "&H27 -> FY 2020 | I28: ="FY "&I27 -> FY 2021 | J28: ="FY "&J27 -> FY 2022 | ... AA28: ="FY "&AA27 -> FY 2039 | AB28: Perpetuity
B29: Net Operating Working Capital % Rev | C29: ='2. Integrated Finance'!C59/'2. Integrated Finance'!C9 -> 0.016850444 | D29: ='2. Integrated Finance'!D59/'2. Integrated Finance'!D9 -> 0.010020689 | E29: ='2. Integrated Finance'!E59/'2. Integrated Finance'!E9 -> 0.047469938 | F29: ='2. Integrated Finance'!F59/'2. Integrated Finance'!F9 -> 0.27549101 | G29: ='2. Integrated Finance'!G59/'2. Integrated Finance'!G9 -> -0.019420113 | H29: ='2. Integrated Finance'!H59/'2. Integrated Finance'!H9 -> 0.019542478 | I29: ='2. Integrated Finance'!I59/'2. Integrated Finance'!I9 -> 0.055229417 | J29: ='2. Integrated Finance'!J59/'2. Integrated Finance'!J9 -> -0.06614202 | ... L29: ='2. Integrated Finance'!L59/'2. Integrated Finance'!L9 -> -0.061438183 | M29: =AVERAGE($C$29:$L$29) -> 0.022084574 | N29: =AVERAGE($C$29:$L$29) -> 0.022084574 | O29: =AVERAGE($C$29:$L$29) -> 0.022084574 | P29: =AVERAGE($C$29:$L$29) -> 0.022084574 | Q29: =AVERAGE($C$29:$L$29) -> 0.022084574 | R29: =AVERAGE($C$29:$L$29) -> 0.022084574 | S29: =AVERAGE($C$29:$L$29) -> 0.022084574 | T29: =AVERAGE($C$29:$L$29) -> 0.022084574 | ... AB29: =AVERAGE($C$29:$L$29) -> 0.022084574
B30: Net Operating Long-Term Assets % Rev | C30: ='2. Integrated Finance'!C63/'2. Integrated Finance'!C9 -> 0.18198897 | D30: ='2. Integrated Finance'!D63/'2. Integrated Finance'!D9 -> 0.18033956 | E30: ='2. Integrated Finance'!E63/'2. Integrated Finance'!E9 -> 0.1860114 | F30: ='2. Integrated Finance'!F63/'2. Integrated Finance'!F9 -> -0.092117559 | G30: ='2. Integrated Finance'!G63/'2. Integrated Finance'!G9 -> -0.063496375 | H30: ='2. Integrated Finance'!H63/'2. Integrated Finance'!H9 -> -0.033676333 | I30: ='2. Integrated Finance'!I63/'2. Integrated Finance'!I9 -> -0.011469137 | J30: ='2. Integrated Finance'!J63/'2. Integrated Finance'!J9 -> 0.005292974 | ... L30: ='2. Integrated Finance'!L63/'2. Integrated Finance'!L9 -> 0.07077305 | M30: =AVERAGE($C$30:$L$30) -> 0.045865083 | N30: =AVERAGE($C$30:$L$30) -> 0.045865083 | O30: =AVERAGE($C$30:$L$30) -> 0.045865083 | P30: =AVERAGE($C$30:$L$30) -> 0.045865083 | Q30: =AVERAGE($C$30:$L$30) -> 0.045865083 | R30: =AVERAGE($C$30:$L$30) -> 0.045865083 | S30: =AVERAGE($C$30:$L$30) -> 0.045865083 | T30: =AVERAGE($C$30:$L$30) -> 0.045865083 | ... AB30: =AVERAGE($C$30:$L$30) -> 0.045865083
B31: Goodwill & Intangibles % Rev | C31: ='2. Integrated Finance'!C65/'2. Integrated Finance'!C9 -> 0.10936872 | D31: ='2. Integrated Finance'!D65/'2. Integrated Finance'!D9 -> 0.10489353 | E31: ='2. Integrated Finance'!E65/'2. Integrated Finance'!E9 -> 0.088471778 | F31: ='2. Integrated Finance'!F65/'2. Integrated Finance'!F9 -> 0.18543255 | G31: ='2. Integrated Finance'!G65/'2. Integrated Finance'!G9 -> 0.16117788 | H31: ='2. Integrated Finance'!H65/'2. Integrated Finance'!H9 -> 0.17643082 | I31: ='2. Integrated Finance'!I65/'2. Integrated Finance'!I9 -> 0.13857938 | J31: ='2. Integrated Finance'!J65/'2. Integrated Finance'!J9 -> 0.10664707 | ... L31: ='2. Integrated Finance'!L65/'2. Integrated Finance'!L9 -> 0.094443308 | M31: =AVERAGE($C$31:$L$31) -> 0.12582524 | N31: =AVERAGE($C$31:$L$31) -> 0.12582524 | O31: =AVERAGE($C$31:$L$31) -> 0.12582524 | P31: =AVERAGE($C$31:$L$31) -> 0.12582524 | Q31: =AVERAGE($C$31:$L$31) -> 0.12582524 | R31: =AVERAGE($C$31:$L$31) -> 0.12582524 | S31: =AVERAGE($C$31:$L$31) -> 0.12582524 | T31: =AVERAGE($C$31:$L$31) -> 0.12582524 | ... AB31: =AVERAGE($C$31:$L$31) -> 0.12582524
B32: Other Long-Term Assets % YoY | C32: ='2. Integrated Finance'!C69/'2. Integrated Finance'!C9 -> 0.11800007 | D32: ='2. Integrated Finance'!D69/'2. Integrated Finance'!D9 -> 0.1313245 | E32: ='2. Integrated Finance'!E69/'2. Integrated Finance'!E9 -> 0.097472618 | F32: ='2. Integrated Finance'!F69/'2. Integrated Finance'!F9 -> 0.046493659 | G32: ='2. Integrated Finance'!G69/'2. Integrated Finance'!G9 -> 0.10794233 | H32: ='2. Integrated Finance'!H69/'2. Integrated Finance'!H9 -> 0.12940301 | I32: ='2. Integrated Finance'!I69/'2. Integrated Finance'!I9 -> 0.10335299 | J32: ='2. Integrated Finance'!J69/'2. Integrated Finance'!J9 -> 0.091292174 | ... L32: ='2. Integrated Finance'!L69/'2. Integrated Finance'!L9 -> 0.08634406 | M32: =AVERAGE($C$32:$L$32) -> 0.099511534 | N32: =AVERAGE($C$32:$L$32) -> 0.099511534 | O32: =AVERAGE($C$32:$L$32) -> 0.099511534 | P32: =AVERAGE($C$32:$L$32) -> 0.099511534 | Q32: =AVERAGE($C$32:$L$32) -> 0.099511534 | R32: =AVERAGE($C$32:$L$32) -> 0.099511534 | S32: =AVERAGE($C$32:$L$32) -> 0.099511534 | T32: =AVERAGE($C$32:$L$32) -> 0.099511534 | ... AB32: =AVERAGE($C$32:$L$32) -> 0.099511534
B34: Long Term Debt % YoY | D34: =('2. Integrated Finance'!D84-'2. Integrated Finance'!C84)/'2. Integrated Finance'!C84 -> 0.36408946 | E34: =('2. Integrated Finance'!E84-'2. Integrated Finance'!D84)/'2. Integrated Finance'!D84 -> 0.22809319 | F34: =('2. Integrated Finance'!F84-'2. Integrated Finance'!E84)/'2. Integrated Finance'!E84 -> 1.3114988 | G34: =('2. Integrated Finance'!G84-'2. Integrated Finance'!F84)/'2. Integrated Finance'!F84 -> 0.22846582 | H34: =('2. Integrated Finance'!H84-'2. Integrated Finance'!G84)/'2. Integrated Finance'!G84 -> 0.99886272 | I34: =('2. Integrated Finance'!I84-'2. Integrated Finance'!H84)/'2. Integrated Finance'!H84 -> -0.043294969 | J34: =('2. Integrated Finance'!J84-'2. Integrated Finance'!I84)/'2. Integrated Finance'!I84 -> -0.03370655 | K34: =('2. Integrated Finance'!K84-'2. Integrated Finance'!J84)/'2. Integrated Finance'!J84 -> 0.040576493 | L34: =('2. Integrated Finance'!L84-'2. Integrated Finance'!K84)/'2. Integrated Finance'!K84 -> 0.075385146 | M34: 0.04 | N34: 0.04 | O34: 0.03 | P34: 0.03 | Q34: 0.03 | R34: 0.03 | S34: 0.02 | T34: 0.02 | U34: 0.02 | V34: 0.02 | W34: 0.02 | X34: 0.02 | Y34: 0.02 | Z34: 0.02 | AA34: 0.02 | AB34: 0.02
B35: Dividend Payout % Net Income | C35: =-'2. Integrated Finance'!C78/'2. Integrated Finance'!C77 -> 0.36853558 | D35: =-'2. Integrated Finance'!D78/'2. Integrated Finance'!D77 -> 0.44227561 | E35: =-'2. Integrated Finance'!E78/'2. Integrated Finance'!E77 -> 0.52549659 | F35: =-'2. Integrated Finance'!F78/'2. Integrated Finance'!F77 -> 0.3896377 | G35: =-'2. Integrated Finance'!G78/'2. Integrated Finance'!G77 -> 0.50055568 | H35: =-'2. Integrated Finance'!H78/'2. Integrated Finance'!H77 -> 1.5475601 | I35: =-'2. Integrated Finance'!I78/'2. Integrated Finance'!I77 -> 0.64229753 | J35: =-'2. Integrated Finance'!J78/'2. Integrated Finance'!J77 -> 0.69889688 | ... L35: =-'2. Integrated Finance'!L78/'2. Integrated Finance'!L77 -> 0.69797123 | M35: =AVERAGE($C$35:$L$35) -> 0.64132026 | N35: =AVERAGE($C$35:$L$35) -> 0.64132026 | O35: =AVERAGE($C$35:$L$35) -> 0.64132026 | P35: =AVERAGE($C$35:$L$35) -> 0.64132026 | Q35: =AVERAGE($C$35:$L$35) -> 0.64132026 | R35: =AVERAGE($C$35:$L$35) -> 0.64132026 | S35: =AVERAGE($C$35:$L$35) -> 0.64132026 | T35: =AVERAGE($C$35:$L$35) -> 0.64132026 | ... AB35: =AVERAGE($C$35:$L$35) -> 0.64132026
B36: Issued Equity % YoY | D36: =('2. Integrated Finance'!D89-'2. Integrated Finance'!C89)/'2. Integrated Finance'!C89 -> 0 | E36: =('2. Integrated Finance'!E89-'2. Integrated Finance'!D89)/'2. Integrated Finance'!D89 -> -0.0023474178 | F36: =('2. Integrated Finance'!F89-'2. Integrated Finance'!E89)/'2. Integrated Finance'!E89 -> -0.0023529412 | G36: =('2. Integrated Finance'!G89-'2. Integrated Finance'!F89)/'2. Integrated Finance'!F89 -> -0.0023584906 | H36: =('2. Integrated Finance'!H89-'2. Integrated Finance'!G89)/'2. Integrated Finance'!G89 -> 7.8676123 | I36: =('2. Integrated Finance'!I89-'2. Integrated Finance'!H89)/'2. Integrated Finance'!H89 -> 1.2588643 | J36: =('2. Integrated Finance'!J89-'2. Integrated Finance'!I89)/'2. Integrated Finance'!I89 -> -0.75640269 | K36: =('2. Integrated Finance'!K89-'2. Integrated Finance'!J89)/'2. Integrated Finance'!J89 -> -0.81007752 | L36: =('2. Integrated Finance'!L89-'2. Integrated Finance'!K89)/'2. Integrated Finance'!K89 -> 7.2576531 | M36: -0.01 | N36: -0.02 | O36: 0 | P36: 0 | Q36: 0 | R36: 0 | S36: 0.01 | T36: 0.01 | U36: 0.01 | V36: 0.01 | W36: 0.01 | X36: 0.01 | Y36: 0.01 | Z36: 0.01 | AA36: 0.01 | AB36: 0.01 | AC36: We analysed the movement in equity between the years 2015-2024 and noticed that it was extremely volatile, indicating that Starbucks' equity base has fluctuated drastically because of massive share-buybacks and retained earnings swings. Therefore, for the purpose of our estimation, we have removed the anomalous years, and took the remaining normal years giving us an average of -0.18%. This is exactly flat to slightly negative equity growth, which makes sense for a company consistently repurchasing shares.
I38: \

Sheet 4. Market Data & WACC
B1: ***Source: Bloomberg
B2: WACC
B3: 2015 | C3: =B3+1 -> 2016 | D3: =C3+1 -> 2017 | E3: =D3+1 -> 2018 | F3: =E3+1 -> 2019 | G3: =F3+1 -> 2020 | H3: =G3+1 -> 2021 | I3: =H3+1 -> 2022 | J3: =I3+1 -> 2023 | K3: =J3+1 -> 2024
B4: 0.085 | C4: 0.083 | D4: 0.092 | E4: 0.084 | F4: 0.071 | G4: 0.073 | H4: 0.099 | I4: 0.082 | J4: 0.091 | K4: 0.089
B6: Average WACC
B7: =AVERAGE(B4:K4) -> 0.0849
B9: Cost of Equity
B10: =B3 -> 2015 | C10: =C3 -> 2016 | D10: =D3 -> 2017 | E10: =E3 -> 2018 | F10: =F3 -> 2019 | G10: =G3 -> 2020 | H10: =H3 -> 2021 | I10: =I3 -> 2022 | ... K10: =K3 -> 2024
B11: 0.087 | C11: 0.086 | D11: 0.096 | E11: 0.09 | F11: 0.077 | G11: 0.09 | H11: 0.114 | I11: 0.092 | J11: 0.101 | K11: 0.101
B13: Average COE
B14: =AVERAGE(B11:K11) -> 0.0934

Sheet 5. Re-org Fin Stmts
B2: Re-organizing Financial Statements - Starbucks US
B5: INCOME STATEMENT
B6: PARTICULARS | C6: ACTUALS | M6: NEAR TERM FORECAST | R6: FAR TERM FORECAST | AB6: CV
C7: =2015 -> 2015 | D7: =C7+1 -> 2016 | E7: =D7+1 -> 2017 | F7: =E7+1 -> 2018 | G7: =F7+1 -> 2019 | H7: =G7+1 -> 2020 | I7: =H7+1 -> 2021 | J7: =I7+1 -> 2022 | K7: =J7+1 -> 2023 | ... BV7: =BU7+1 -> 2086
C8: ="FY "&C7 -> FY 2015 | D8: ="FY "&D7 -> FY 2016 | E8: ="FY "&E7 -> FY 2017 | F8: ="FY "&F7 -> FY 2018 | G8: ="FY "&G7 -> FY 2019 | H8: ="FY "&H7 -> FY 2020 | I8: ="FY "&I7 -> FY 2021 | J8: ="FY "&J7 -> FY 2022 | ... AA8: ="FY "&AA7 -> FY 2039 | AB8: Perpetuity
B9: Operating Profit after Tax | C9: ='2. Integrated Finance'!C24-'2. Integrated Finance'!C39 -> 2511.9 | D9: ='2. Integrated Finance'!D24-'2. Integrated Finance'!D39 -> 2792.2 | E9: ='2. Integrated Finance'!E24-'2. Integrated Finance'!E39 -> 2918.6 | F9: ='2. Integrated Finance'!F24-'2. Integrated Finance'!F39 -> 3233 | G9: ='2. Integrated Finance'!G24-'2. Integrated Finance'!G39 -> 3698.9 | H9: ='2. Integrated Finance'!H24-'2. Integrated Finance'!H39 -> 1893.5 | I9: ='2. Integrated Finance'!I24-'2. Integrated Finance'!I39 -> 4061.3 | J9: ='2. Integrated Finance'!J24-'2. Integrated Finance'!J39 -> 3906.5 | ... AB9: ='2. Integrated Finance'!AB24-'2. Integrated Finance'!AB39 -> 19934.728
B10: Less: Interest Tax Shield | C10: ='2. Integrated Finance'!C47 -> 20.658686 | D10: ='2. Integrated Finance'!D47 -> 26.715955 | E10: ='2. Integrated Finance'!E47 -> 30.692646 | F10: ='2. Integrated Finance'!F47 -> 37.183149 | G10: ='2. Integrated Finance'!G47 -> 64.596212 | H10: ='2. Integrated Finance'!H47 -> 89.95955 | I10: ='2. Integrated Finance'!I47 -> 101.43379 | J10: ='2. Integrated Finance'!J47 -> 108.23286 | ... AB10: ='2. Integrated Finance'!AB47 -> 71.385403
B11: NOPLAT | C11: =C9-C10 -> 2491.2413 | D11: =D9-D10 -> 2765.484 | E11: =E9-E10 -> 2887.9074 | F11: =F9-F10 -> 3195.8169 | G11: =G9-G10 -> 3634.3038 | H11: =H9-H10 -> 1803.5405 | I11: =I9-I10 -> 3959.8662 | J11: =J9-J10 -> 3798.2671 | ... AB11: =AB9-AB10 -> 19863.342
B12: Interest Expense after Tax | C12: ='2. Integrated Finance'!C28-'2. Integrated Finance'!C47 -> 49.841314 | D12: ='2. Integrated Finance'!D28-'2. Integrated Finance'!D47 -> 54.584045 | E12: ='2. Integrated Finance'!E28-'2. Integrated Finance'!E47 -> 61.807354 | F12: ='2. Integrated Finance'!F28-'2. Integrated Finance'!F47 -> 133.11685 | G12: ='2. Integrated Finance'!G28-'2. Integrated Finance'!G47 -> 266.40379 | H12: ='2. Integrated Finance'!H28-'2. Integrated Finance'!H47 -> 347.04045 | I12: ='2. Integrated Finance'!I28-'2. Integrated Finance'!I47 -> 368.36621 | J12: ='2. Integrated Finance'!J28-'2. Integrated Finance'!J47 -> 374.66714 | ... AB12: ='2. Integrated Finance'!AB28-'2. Integrated Finance'!AB47 -> 253.3546
B14: BALANCE SHEET
B15: PARTICULARS | C15: ACTUALS | M15: NEAR TERM FORECAST | R15: FAR TERM FORECAST | AB15: CV
C16: =2015 -> 2015 | D16: =C16+1 -> 2016 | E16: =D16+1 -> 2017 | F16: =E16+1 -> 2018 | G16: =F16+1 -> 2019 | H16: =G16+1 -> 2020 | I16: =H16+1 -> 2021 | J16: =I16+1 -> 2022 | K16: =J16+1 -> 2023 | ... BV16: =BU16+1 -> 2086
C17: ="FY "&C16 -> FY 2015 | D17: ="FY "&D16 -> FY 2016 | E17: ="FY "&E16 -> FY 2017 | F17: ="FY "&F16 -> FY 2018 | G17: ="FY "&G16 -> FY 2019 | H17: ="FY "&H16 -> FY 2020 | I17: ="FY "&I16 -> FY 2021 | J17: ="FY "&J16 -> FY 2022 | ... AA17: ="FY "&AA16 -> FY 2039 | AB17: Perpetuity
B18: Opening Working Capital | D18: =C20 -> 322.9 | E18: =D20 -> 213.6 | F18: =E20 -> 1062.7 | G18: =F20 -> 6810 | H18: =G20 -> -514.8 | I18: =H20 -> 459.6 | J18: =I20 -> 1605 | K18: =J20 -> -2133.1 | ... AB18: =AA20 -> 2679.4318
B19: Change in Working Capital | D19: =D20-D18 -> -109.3 | E19: =E20-E18 -> 849.1 | F19: =F20-F18 -> 5747.3 | G19: =G20-G18 -> -7324.8 | H19: =H20-H18 -> 974.4 | I19: =I20-I18 -> 1145.4 | J19: =J20-J18 -> -3738.1 | K19: =K20-K18 -> 91.2 | ... AB19: =AB20-AB18 -> 231.89202
B20: Closing Working Capital | C20: ='2. Integrated Finance'!C59 -> 322.9 | D20: ='2. Integrated Finance'!D59 -> 213.6 | E20: ='2. Integrated Finance'!E59 -> 1062.7 | F20: ='2. Integrated Finance'!F59 -> 6810 | G20: ='2. Integrated Finance'!G59 -> -514.8 | H20: ='2. Integrated Finance'!H59 -> 459.6 | I20: ='2. Integrated Finance'!I59 -> 1605 | J20: ='2. Integrated Finance'!J59 -> -2133.1 | ... AB20: ='2. Integrated Finance'!AB59 -> 2911.3238
B22: Opening Net Long-term Assets | D22: =C24 -> 3487.4 | E22: =D24 -> 3844.1 | F22: =E24 -> 4164.2 | G22: =F24 -> -2277.1 | H22: =G24 -> -1683.2 | I22: =H24 -> -792 | J22: =I24 -> -333.3 | K22: =J24 -> 170.7 | ... AB22: =AA24 -> 5564.6243
B23: Change in Net Long-term Assets | D23: =D24-D22 -> 356.7 | E23: =E24-E22 -> 320.1 | F23: =F24-F22 -> -6441.3 | G23: =G24-G22 -> 593.9 | H23: =H24-H22 -> 891.2 | I23: =I24-I22 -> 458.7 | J23: =J24-J22 -> 504 | K23: =K24-K22 -> 1088.6 | ... AB23: =AB24-AB22 -> 481.59165
B24: Closing Net Long-term Assets | C24: ='2. Integrated Finance'!C63 -> 3487.4 | D24: ='2. Integrated Finance'!D63 -> 3844.1 | E24: ='2. Integrated Finance'!E63 -> 4164.2 | F24: ='2. Integrated Finance'!F63 -> -2277.1 | G24: ='2. Integrated Finance'!G63 -> -1683.2 | H24: ='2. Integrated Finance'!H63 -> -792 | I24: ='2. Integrated Finance'!I63 -> -333.3 | J24: ='2. Integrated Finance'!J63 -> 170.7 | ... AB24: ='2. Integrated Finance'!AB63 -> 6046.216
B26: Depreciation | C26: ='1. Raw Data - Bloomberg'!D79 -> 843.9 | D26: ='1. Raw Data - Bloomberg'!E79 -> 923.5 | E26: ='1. Raw Data - Bloomberg'!F79 -> 953.9 | F26: ='1. Raw Data - Bloomberg'!G79 -> 1060.5 | G26: ='1. Raw Data - Bloomberg'!H79 -> 1144.5 | H26: ='1. Raw Data - Bloomberg'!I79 -> 1207.6 | I26: ='1. Raw Data - Bloomberg'!J79 -> 1218.3 | J26: ='1. Raw Data - Bloomberg'!K79 -> 1255.2 | ... L26: ='1. Raw Data - Bloomberg'!M79 -> 1492.2 | M26: ='2. Integrated Finance'!M9*'3. Historical & Forecast Ratio '!M23 -> 1669.2503 | N26: ='2. Integrated Finance'!N9*'3. Historical & Forecast Ratio '!N23 -> 1805.6371 | O26: ='2. Integrated Finance'!O9*'3. Historical & Forecast Ratio '!O23 -> 1954.0191 | P26: ='2. Integrated Finance'!P9*'3. Historical & Forecast Ratio '!P23 -> 2115.4652 | Q26: ='2. Integrated Finance'!Q9*'3. Historical & Forecast Ratio '!Q23 -> 2291.1414 | R26: ='2. Integrated Finance'!R9*'3. Historical & Forecast Ratio '!R23 -> 2482.3203 | S26: ='2. Integrated Finance'!S9*'3. Historical & Forecast Ratio '!S23 -> 2690.3907 | T26: ='2. Integrated Finance'!T9*'3. Historical & Forecast Ratio '!T23 -> 2916.8689 | ... AB26: ='2. Integrated Finance'!AB9*'3. Historical & Forecast Ratio '!AB23 -> 5625.8968
B28: Net Capex | D28: =D23+D26 -> 1280.2 | E28: =E23+E26 -> 1274 | F28: =F23+F26 -> -5380.8 | G28: =G23+G26 -> 1738.4 | H28: =H23+H26 -> 2098.8 | I28: =I23+I26 -> 1677 | J28: =J23+J26 -> 1759.2 | K28: =K23+K26 -> 2429.7 | ... AB28: =AB23+AB26 -> 6107.4885
B30: Opening Debt | D30: =C32 -> 2347.5 | E30: =D32 -> 3202.2 | F30: =E32 -> 3932.6 | G30: =F32 -> 9090.2 | H30: =G32 -> 11167 | I30: =H32 -> 22321.3 | J30: =I32 -> 21354.9 | K30: =J32 -> 20635.1 | ... AB30: =AA32 -> 33594.002
B31: Increase (Decrease) in Debt | D31: =D32-D30 -> 854.7 | E31: =E32-E30 -> 730.4 | F31: =F32-F30 -> 5157.6 | G31: =G32-G30 -> 2076.8 | H31: =H32-H30 -> 11154.3 | I31: =I32-I30 -> -966.4 | J31: =J32-J30 -> -719.8 | K31: =K32-K30 -> 837.3 | ... AB31: =AB32-AB30 -> 671.88004
B32: Closing Debt | C32: ='2. Integrated Finance'!C84 -> 2347.5 | D32: ='2. Integrated Finance'!D84 -> 3202.2 | E32: ='2. Integrated Finance'!E84 -> 3932.6 | F32: ='2. Integrated Finance'!F84 -> 9090.2 | G32: ='2. Integrated Finance'!G84 -> 11167 | H32: ='2. Integrated Finance'!H84 -> 22321.3 | I32: ='2. Integrated Finance'!I84 -> 21354.9 | J32: ='2. Integrated Finance'!J84 -> 20635.1 | ... AB32: ='2. Integrated Finance'!AB84 -> 34265.882

Sheet 6. ROIC & FCF
B2: ROIC & FCF - Starbucks US
B5: PARTICULARS | C5: ACTUALS | M5: NEAR TERM FORECAST | R5: FAR TERM FORECAST | AB5: CV
C6: =2015 -> 2015 | D6: =C6+1 -> 2016 | E6: =D6+1 -> 2017 | F6: =E6+1 -> 2018 | G6: =F6+1 -> 2019 | H6: =G6+1 -> 2020 | I6: =H6+1 -> 2021 | J6: =I6+1 -> 2022 | K6: =J6+1 -> 2023 | ... BV6: =BU6+1 -> 2086
C7: ="FY "&C6 -> FY 2015 | D7: ="FY "&D6 -> FY 2016 | E7: ="FY "&E6 -> FY 2017 | F7: ="FY "&F6 -> FY 2018 | G7: ="FY "&G6 -> FY 2019 | H7: ="FY "&H6 -> FY 2020 | I7: ="FY "&I6 -> FY 2021 | J7: ="FY "&J6 -> FY 2022 | ... AA7: ="FY "&AA6 -> FY 2039 | AB7: Perpetuity
B8: NOPLAT | D8: ='5. Re-org Fin Stmts'!D11 -> 2765.484 | E8: ='5. Re-org Fin Stmts'!E11 -> 2887.9074 | F8: ='5. Re-org Fin Stmts'!F11 -> 3195.8169 | G8: ='5. Re-org Fin Stmts'!G11 -> 3634.3038 | H8: ='5. Re-org Fin Stmts'!H11 -> 1803.5405 | I8: ='5. Re-org Fin Stmts'!I11 -> 3959.8662 | J8: ='5. Re-org Fin Stmts'!J11 -> 3798.2671 | K8: ='5. Re-org Fin Stmts'!K11 -> 4394.1369 | ... AB8: ='5. Re-org Fin Stmts'!AB11 -> 19863.342
B9: Change in Working Capital | D9: ='5. Re-org Fin Stmts'!D19 -> -109.3 | E9: ='5. Re-org Fin Stmts'!E19 -> 849.1 | F9: ='5. Re-org Fin Stmts'!F19 -> 5747.3 | G9: ='5. Re-org Fin Stmts'!G19 -> -7324.8 | H9: ='5. Re-org Fin Stmts'!H19 -> 974.4 | I9: ='5. Re-org Fin Stmts'!I19 -> 1145.4 | J9: ='5. Re-org Fin Stmts'!J19 -> -3738.1 | K9: ='5. Re-org Fin Stmts'!K19 -> 91.2 | ... AB9: ='5. Re-org Fin Stmts'!AB19 -> 231.89202
B10: Net Capex | D10: ='5. Re-org Fin Stmts'!D28 -> 1280.2 | E10: ='5. Re-org Fin Stmts'!E28 -> 1274 | F10: ='5. Re-org Fin Stmts'!F28 -> -5380.8 | G10: ='5. Re-org Fin Stmts'!G28 -> 1738.4 | H10: ='5. Re-org Fin Stmts'!H28 -> 2098.8 | I10: ='5. Re-org Fin Stmts'!I28 -> 1677 | J10: ='5. Re-org Fin Stmts'!J28 -> 1759.2 | K10: ='5. Re-org Fin Stmts'!K28 -> 2429.7 | ... AB10: ='5. Re-org Fin Stmts'!AB28 -> 6107.4885
B11: FCFF | D11: =D8-D9-D10 -> 1594.584 | E11: =E8-E9-E10 -> 764.80735 | F11: =F8-F9-F10 -> 2829.3169 | G11: =G8-G9-G10 -> 9220.7038 | H11: =H8-H9-H10 -> -1269.6595 | I11: =I8-I9-I10 -> 1137.4662 | J11: =J8-J9-J10 -> 5777.1671 | K11: =K8-K9-K10 -> 1873.2369 | ... AB11: =AB8-AB9-AB10 -> 13523.962
B13: Less: Interest Expense after Tax | D13: ='5. Re-org Fin Stmts'!D12 -> 54.584045 | E13: ='5. Re-org Fin Stmts'!E12 -> 61.807354 | F13: ='5. Re-org Fin Stmts'!F12 -> 133.11685 | G13: ='5. Re-org Fin Stmts'!G12 -> 266.40379 | H13: ='5. Re-org Fin Stmts'!H12 -> 347.04045 | I13: ='5. Re-org Fin Stmts'!I12 -> 368.36621 | J13: ='5. Re-org Fin Stmts'!J12 -> 374.66714 | K13: ='5. Re-org Fin Stmts'!K12 -> 420.03693 | ... AB13: ='5. Re-org Fin Stmts'!AB12 -> 253.3546
B14: Add/(Less) : Increase/(Decrease) in Debt | D14: ='5. Re-org Fin Stmts'!D31 -> 854.7 | E14: ='5. Re-org Fin Stmts'!E31 -> 730.4 | F14: ='5. Re-org Fin Stmts'!F31 -> 5157.6 | G14: ='5. Re-org Fin Stmts'!G31 -> 2076.8 | H14: ='5. Re-org Fin Stmts'!H31 -> 11154.3 | I14: ='5. Re-org Fin Stmts'!I31 -> -966.4 | J14: ='5. Re-org Fin Stmts'!J31 -> -719.8 | K14: ='5. Re-org Fin Stmts'!K31 -> 837.3 | ... AB14: ='5. Re-org Fin Stmts'!AB31 -> 671.88004
B15: FCFE | D15: =D11-D13+D14 -> 2394.7 | E15: =E11-E13+E14 -> 1433.4 | F15: =F11-F13+F14 -> 7853.8 | G15: =G11-G13+G14 -> 11031.1 | H15: =H11-H13+H14 -> 9537.6 | I15: =I11-I13+I14 -> -197.3 | J15: =J11-J13+J14 -> 4682.7 | K15: =K11-K13+K14 -> 2290.5 | ... AB15: =AB11-AB13+AB14 -> 13942.487
B18: NOPLAT | D18: =D8 -> 2765.484 | E18: =E8 -> 2887.9074 | F18: =F8 -> 3195.8169 | G18: =G8 -> 3634.3038 | H18: =H8 -> 1803.5405 | I18: =I8 -> 3959.8662 | J18: =J8 -> 3798.2671 | K18: =K8 -> 4394.1369 | ... AB18: =AB8 -> 19863.342
B19: Invested Capital | D19: ='2. Integrated Finance'!D67 -> 6293.6 | E19: ='2. Integrated Finance'!E67 -> 7207.5 | F19: ='2. Integrated Finance'!F67 -> 9116.7 | G19: ='2. Integrated Finance'!G67 -> 2074.6 | H19: ='2. Integrated Finance'!H67 -> 3816.9 | I19: ='2. Integrated Finance'!I67 -> 5298.9 | J19: ='2. Integrated Finance'!J67 -> 1477 | K19: ='2. Integrated Finance'!K67 -> 2556.2 | ... AB19: ='2. Integrated Finance'!AB67 -> 25544.593
B20: ROIC | D20: =D18/D19 -> 0.43941211 | E20: =E18/E19 -> 0.40068087 | F20: =F18/F19 -> 0.35054536 | G20: =G18/G19 -> 1.7518094 | H20: =H18/H19 -> 0.47251446 | I20: =I18/I19 -> 0.74729967 | J20: =J18/J19 -> 2.5716094 | K20: =K18/K19 -> 1.7190114 | ... AB20: =AB18/AB19 -> 0.77759479
C21: 0.3636 | D21: 0.3105 | E21: 0.2612 | F21: 0.2865 | G21: 0.3498 | H21: 0.0906 | I21: 0.1911 | J21: 0.1898 | K21: 0.2508 | L21: 0.2103
D23: =D18/D21 -> 8906.5509 | E23: =E18/E21 -> 11056.307 | F23: =F18/F21 -> 11154.684 | G23: =G18/G21 -> 10389.662 | H23: =H18/H21 -> 19906.627 | I23: =I18/I21 -> 20721.435 | J23: =J18/J21 -> 20011.945 | K23: =K18/K21 -> 17520.482 | L23: =L18/L21 -> 19907.13
D24: =D23-D19 -> 2612.9509 | E24: =E23-E19 -> 3848.8069 | F24: =F23-F19 -> 2037.9836 | G24: =G23-G19 -> 8315.0621 | H24: =H23-H19 -> 16089.727 | I24: =I23-I19 -> 15422.535 | J24: =J23-J19 -> 18534.945 | K24: =K23-K19 -> 14964.282 | L24: =L23-L19 -> 16152.83
D27: 9782.6 | E27: =D18/D27 -> 0.28269418

Sheet 7. Valuation
B2: Valuation - Starbucks US
B5: PARTICULARS | D5: NEAR TERM FORECAST | I5: FAR TERM FORECAST | S5: CV
C6: 2024 | D6: =C6+1 -> 2025 | E6: =D6+1 -> 2026 | F6: =E6+1 -> 2027 | G6: =F6+1 -> 2028 | H6: =G6+1 -> 2029 | I6: =H6+1 -> 2030 | J6: =I6+1 -> 2031 | K6: =J6+1 -> 2032 | ... BM6: =BL6+1 -> 2086
C7: ="FY "&C6 -> FY 2024 | D7: ="FY "&D6 -> FY 2025 | E7: ="FY "&E6 -> FY 2026 | F7: ="FY "&F6 -> FY 2027 | G7: ="FY "&G6 -> FY 2028 | H7: ="FY "&H6 -> FY 2029 | I7: ="FY "&I6 -> FY 2030 | J7: ="FY "&J6 -> FY 2031 | ... R7: ="FY "&R6 -> FY 2039 | S7: Perpetuity
B8: FCFF Valuation Model:
B9: t | C9: 0 | D9: =C9+1 -> 1 | E9: =D9+1 -> 2 | F9: =E9+1 -> 3 | G9: =F9+1 -> 4 | H9: =G9+1 -> 5 | I9: =H9+1 -> 6 | J9: =I9+1 -> 7 | K9: =J9+1 -> 8 | ... S9: =R9+1 -> 16
B10: g | S10: ='Sensitivity Analysis'!C6 -> 0.035
B11: WACC | S11: ='Sensitivity Analysis'!C7 -> 0.0849
B12: FCFF | C12: ='6. ROIC & FCF'!L11 -> 1573.9694 | D12: ='6. ROIC & FCF'!M11 -> 1442.6084 | E12: ='6. ROIC & FCF'!N11 -> 3510.6448 | F12: ='6. ROIC & FCF'!O11 -> 4102.4206 | G12: ='6. ROIC & FCF'!P11 -> 4332.7038 | H12: ='6. ROIC & FCF'!Q11 -> 4859.9788 | I12: ='6. ROIC & FCF'!R11 -> 5262.9259 | J12: ='6. ROIC & FCF'!S11 -> 5821.8226 | ... S12: ='6. ROIC & FCF'!AB11 -> 13523.962
B13: PV of FCFF | D13: =D12/(1+$S$11)^D9 -> 1329.7156 | E13: =E12/(1+$S$11)^E9 -> 2982.6856 | F13: =F12/(1+$S$11)^F9 -> 3212.7065 | G13: =G12/(1+$S$11)^G9 -> 3127.5205 | H13: =H12/(1+$S$11)^H9 -> 3233.5965 | I13: =I12/(1+$S$11)^I9 -> 3227.6691 | J13: =J12/(1+$S$11)^J9 -> 3291.0237 | K13: =K12/(1+$S$11)^K9 -> 3315.0193 | ... R13: =R12/(1+$S$11)^R9 -> 3624.9266
B14: Continuing Value | R14: =S12/(S11-S10) -> 271021.28
B15: PV of Continuing Value | R15: =R14/(1+$S$11)^R9 -> 79828.461
B16: Enterprise (Firm) Value | D16: =SUM(D13:R13)+R15 -> 127984.73
B17: Total Debt (Book Value of Debt) | D17: ='2. Integrated Finance'!L84+'2. Integrated Finance'!L85 -> 29710.9
B18: Total Equity | D18: =D16-D17 -> 98273.83
B19: Number of Outstanding Shares | D19: ='1. Raw Data - Bloomberg'!M168 -> 1133.5
B20: Intrinsic Value per share | D20: =D18/D19 -> 86.699453
B21: Current Price per share (02/10/2025) | D21: 86.72
B23: FCFE Valuation Model:
B24: t | C24: 0 | D24: =C24+1 -> 1 | E24: =D24+1 -> 2 | F24: =E24+1 -> 3 | G24: =F24+1 -> 4 | H24: =G24+1 -> 5 | I24: =H24+1 -> 6 | J24: =I24+1 -> 7 | K24: =J24+1 -> 8 | ... S24: =R24+1 -> 16
B25: g | S25: =S10 -> 0.035
B26: Cost of Equity | S26: ='4. Market Data & WACC'!B14 -> 0.0934
B27: FCFE | C27: ='6. ROIC & FCF'!L15 -> 2767.2 | D27: ='6. ROIC & FCF'!M15 -> 2112.8978 | E27: ='6. ROIC & FCF'!N15 -> 4217.88 | F27: ='6. ROIC & FCF'!O15 -> 4598.326 | G27: ='6. ROIC & FCF'!P15 -> 4851.087 | H27: ='6. ROIC & FCF'!Q15 -> 5401.5141 | I27: ='6. ROIC & FCF'!R15 -> 5828.3079 | J27: ='6. ROIC & FCF'!S15 -> 6130.6672 | ... S27: ='6. ROIC & FCF'!AB15 -> 13942.487
B28: PV of FCFF | D28: =D27/(1+$S$26)^D24 -> 1932.4107 | E28: =E27/(1+$S$26)^E24 -> 3528.061 | F28: =F27/(1+$S$26)^F24 -> 3517.7304 | G28: =G27/(1+$S$26)^G24 -> 3394.0855 | H28: =H27/(1+$S$26)^H24 -> 3456.3695 | I28: =I27/(1+$S$26)^I24 -> 3410.8928 | J28: =J27/(1+$S$26)^J24 -> 3281.3628 | K28: =K27/(1+$S$26)^K24 -> 3271.0656 | ... R28: =R27/(1+$S$26)^R24 -> 3330.6786
B29: Continuing Value | R29: =S27/(S26-S25) -> 238741.22
B30: PV of Continuing Value | R30: =R29/(1+$S$26)^R24 -> 62552.025
B31: Total Equity | D31: =SUM(D28:R28)+R30 -> 111475.15
B32: Number of Outstanding Shares | D32: =D19 -> 1133.5
B33: Intrinsic Value per share | D33: =D31/D32 -> 98.345961
B34: =B21 -> Current Price per share (02/10/2025) | D34: =D21 -> 86.72

Sheet 7. Valuation (2)
B2: Valuation - Starbucks US
B5: PARTICULARS | D5: NEAR TERM FORECAST | I5: FAR TERM FORECAST | S5: CV
C6: 2024 | D6: =C6+1 -> 2025 | E6: =D6+1 -> 2026 | F6: =E6+1 -> 2027 | G6: =F6+1 -> 2028 | H6: =G6+1 -> 2029 | I6: =H6+1 -> 2030 | J6: =I6+1 -> 2031 | K6: =J6+1 -> 2032 | ... BM6: =BL6+1 -> 2086
C7: ="FY "&C6 -> FY 2024 | D7: ="FY "&D6 -> FY 2025 | E7: ="FY "&E6 -> FY 2026 | F7: ="FY "&F6 -> FY 2027 | G7: ="FY "&G6 -> FY 2028 | H7: ="FY "&H6 -> FY 2029 | I7: ="FY "&I6 -> FY 2030 | J7: ="FY "&J6 -> FY 2031 | ... R7: ="FY "&R6 -> FY 2039 | S7: Perpetuity
B8: FCFF Valuation Model:
B9: t | C9: 0 | D9: =C9+1 -> 1 | E9: =D9+1 -> 2 | F9: =E9+1 -> 3 | G9: =F9+1 -> 4 | H9: =G9+1 -> 5 | I9: =H9+1 -> 6 | J9: =I9+1 -> 7 | K9: =J9+1 -> 8 | ... S9: =R9+1 -> 16
B10: g | S10: 0.025
B11: WACC | S11: 0.095
B12: FCFF | C12: ='6. ROIC & FCF'!L11 -> 1573.9694 | D12: ='6. ROIC & FCF'!M11 -> 1442.6084 | E12: ='6. ROIC & FCF'!N11 -> 3510.6448 | F12: ='6. ROIC & FCF'!O11 -> 4102.4206 | G12: ='6. ROIC & FCF'!P11 -> 4332.7038 | H12: ='6. ROIC & FCF'!Q11 -> 4859.9788 | I12: ='6. ROIC & FCF'!R11 -> 5262.9259 | J12: ='6. ROIC & FCF'!S11 -> 5821.8226 | ... S12: ='6. ROIC & FCF'!AB11 -> 13523.962
B13: PV of FCFF | D13: =D12/(1+$S$11)^D9 -> 1317.4506 | E13: =E12/(1+$S$11)^E9 -> 2927.9163 | F13: =F12/(1+$S$11)^F9 -> 3124.6245 | G13: =G12/(1+$S$11)^G9 -> 3013.7174 | H13: =H12/(1+$S$11)^H9 -> 3087.193 | I13: =I12/(1+$S$11)^I9 -> 3053.1106 | J13: =J12/(1+$S$11)^J9 -> 3084.325 | K13: =K12/(1+$S$11)^K9 -> 3078.1571 | ... R13: =R12/(1+$S$11)^R9 -> 3154.5184
B14: Continuing Value | R14: =S12/(S11-S10) -> 193199.46
B15: PV of Continuing Value | R15: =R14/(1+$S$11)^R9 -> 49521.537
B16: Enterprise (Firm) Value | D16: =SUM(D13:R13)+R15 -> 94066.318
B17: Total Debt (Book Value of Debt) | D17: ='2. Integrated Finance'!L84+'2. Integrated Finance'!L85 -> 29710.9
B18: Total Equity | D18: =D16-D17 -> 64355.418
B19: Number of Outstanding Shares | D19: ='1. Raw Data - Bloomberg'!M168 -> 1133.5
B20: Intrinsic Value per share | D20: =D18/D19 -> 56.775843 | E20: Undervalued - BUY
B21: Current Price per share (02/10/2025) | D21: 86.72
B23: FCFE Valuation Model:
B24: t | C24: 0 | D24: =C24+1 -> 1 | E24: =D24+1 -> 2 | F24: =E24+1 -> 3 | G24: =F24+1 -> 4 | H24: =G24+1 -> 5 | I24: =H24+1 -> 6 | J24: =I24+1 -> 7 | K24: =J24+1 -> 8 | ... S24: =R24+1 -> 16
B25: g | S25: =S10 -> 0.025
B26: Cost of Equity | S26: ='4. Market Data & WACC'!B14 -> 0.0934
B27: FCFE | C27: ='6. ROIC & FCF'!L15 -> 2767.2 | D27: ='6. ROIC & FCF'!M15 -> 2112.8978 | E27: ='6. ROIC & FCF'!N15 -> 4217.88 | F27: ='6. ROIC & FCF'!O15 -> 4598.326 | G27: ='6. ROIC & FCF'!P15 -> 4851.087 | H27: ='6. ROIC & FCF'!Q15 -> 5401.5141 | I27: ='6. ROIC & FCF'!R15 -> 5828.3079 | J27: ='6. ROIC & FCF'!S15 -> 6130.6672 | ... S27: ='6. ROIC & FCF'!AB15 -> 13942.487
B28: PV of FCFF | D28: =D27/(1+$S$26)^D24 -> 1932.4107 | E28: =E27/(1+$S$26)^E24 -> 3528.061 | F28: =F27/(1+$S$26)^F24 -> 3517.7304 | G28: =G27/(1+$S$26)^G24 -> 3394.0855 | H28: =H27/(1+$S$26)^H24 -> 3456.3695 | I28: =I27/(1+$S$26)^I24 -> 3410.8928 | J28: =J27/(1+$S$26)^J24 -> 3281.3628 | K28: =K27/(1+$S$26)^K24 -> 3271.0656 | ... R28: =R27/(1+$S$26)^R24 -> 3330.6786
B29: Continuing Value | R29: =S27/(S26-S25) -> 203837.54
B30: PV of Continuing Value | R30: =R29/(1+$S$26)^R24 -> 53406.992
B31: Total Equity | D31: =SUM(D28:R28)+R30 -> 102330.11
B32: Number of Outstanding Shares | D32: =D19 -> 1133.5
B33: Intrinsic Value per share | D33: =D31/D32 -> 90.278001 | E33: Undervalued - BUY
B34: =B21 -> Current Price per share (02/10/2025) | D34: =D21 -> 86.72

Sheet Scenario Analysis
B1: SCENARIO ANALYSIS
B4: Scenario | C4: WACC | D4: Terminal Growth | E4: Intrinsic Value | F4: Description
B5: Bull | C5: =INDEX(C8:C12, MATCH(B5,B8:B12,0)) -> 0.08 | D5: =INDEX(D8:D12,MATCH(B5,B8:B12,0)) -> 0.05 | E5: =INDEX(F8:F12,MATCH(B5,B8:B12,0)) -> 143.42 | F5: =INDEX(G8:G12,MATCH(B5,B8:B12,0)) -> Strong global growth, pricing power, improved efficiency
B7: Scenario | C7: WACC | D7: Terminal g | F7: Intrinsic Value | G7: Description
B8: Base | C8: 0.0849 | D8: 0.035 | F8: 86.7 | G8: Normalized growth; steady expansion; mid-cycle margins.
B9: Bull | C9: 0.08 | D9: 0.05 | F9: 143.42 | G9: Strong global growth, pricing power, improved efficiency
B10: Bear | C10: 0.09 | D10: 0.03 | F10: 69.21 | G10: consumer demand, margin pressure and slower same-store growth
B11: Stress | C11: 0.095 | D11: 0.025 | F11: 56.78 | G11: Severe slowdown — traffic drops, inflation squeezes margins, slower store rollout.
B12: Aggressive | C12: 0.0875 | D12: 0.045 | F12: 95.19 | G12: Rapid store openings, high reinvestment, moderate margin compression.

Sheet Stock Price
A1: Security | B1: SBUX US Equity
A2: Start Date | B2: 42006
A3: End Date | B3: 45933
A4: Period | B4: D
A5: Currency | B5: USD
A7: Date | B7: PX_LAST | C7: PX_BID
A8: 45933 | B8: #N/A N/A | C8: 86.71
A9: 45932 | B9: 86.72 | C9: 86.73
A10: 45931 | B10: 84.4 | C10: 84.34
A11: 45930 | B11: 84.6 | C11: 84.58
A12: 45929 | B12: 85.64 | C12: 85.64
A13: 45926 | B13: 83.39 | C13: 83.38
A14: 45925 | B14: 83.83 | C14: 83.83
A15: 45924 | B15: 84.27 | C15: 84.25
A16: 45923 | B16: 85.69 | C16: 85.69
A17: 45922 | B17: 85.29 | C17: 85.26
A18: 45919 | B18: 84.56 | C18: 84.55
A19: 45918 | B19: 83.42 | C19: 83.39
A20: 45917 | B20: 83.22 | C20: 83.19
... A40: 45888 | B40: 90.93 | C40: 90.93
A41: 45887 | B41: 92.54 | C41: 92.53 | G41: Table 1 | H41: Company Data | J41: Table 2 | K41: Valuation Results
A42: 45884 | B42: 90.6 | C42: 90.58 | G42: Current Price | H42: $86.72 | J42: DCF (FCFF) | K42: ='7. Valuation'!D20 -> 86.699453
A43: 45883 | B43: 93.06 | C43: 93.03 | G43: Market Cap | H43: 110.3B | J43: DCF (FCFE) | K43: ='7. Valuation'!D33 -> 98.345961
A44: 45882 | B44: 94.18 | C44: 94.16 | G44: Shares o/s | H44: 1.13B | J44: DDM | K44: =DDM!F17 -> 91.294509
A45: 45881 | B45: 93.37 | C45: 93.37 | G45: 52 W High | H45: $17.46
A46: 45880 | B46: 91.74 | C46: 91.75 | G46: EV/EBITDA | H46: 18.3X
A47: 45877 | B47: 92.12 | C47: 92.11
A48: 45876 | B48: 91.02 | C48: 91.05
A49: 45875 | B49: 88.99 | C49: 88.99
A50: 45874 | B50: 90.2 | C50: 90.2
A51: 45873 | B51: 89.78 | C51: 89.77
A52: 45870 | B52: 86.86 | C52: 86.86
A53: 45869 | B53: 89.16 | C53: 89.16
A54: 45868 | B54: 92.76 | C54: 92.76
A55: 45867 | B55: 92.96 | C55: 92.94
A56: 45866 | B56: 93.67 | C56: 93.63
A57: 45863 | B57: 94.42 | C57: 94.4
A58: 45862 | B58: 93.7 | C58: 93.66
... A2712: 42006 | B2712: 40.72 | C2712: 40.705

Sheet Sensitivity Analysis
B1: SENSITIVITY ANALYSIS
B5: Parameters | C5: Value | E5: Terminal Growth | F5: WACC
B6: g | C6: 0.035 | F6: ='7. Valuation'!D20 -> 86.699453 | G6: 0.08 | H6: 0.085 | I6: 0.09 | J6: 0.095
B7: wacc | C7: 0.0849 | F7: 0.025 | G7: 86.331349 | H7: 74.730159 | I7: 65.014918 | J7: 56.775843
B8: Actual Price | C8: ='7. Valuation'!D21 -> 86.72 | F8: 0.03 | G8: 93.169889 | H8: 80.047474 | I8: 69.214348 | J8: 60.136539
F9: 0.035 | G9: 101.52811 | H9: 86.428252 | I9: 74.17731 | J9: 64.057351
F10: 0.04 | G10: 111.97587 | H10: 94.226981 | I10: 80.132866 | J10: 68.691038
F11: 0.045 | G11: 125.40872 | H11: 103.97539 | I11: 87.411877 | J11: 74.251463
F12: 0.05 | G12: 143.31918 | H12: 116.50906 | I12: 96.510642 | J12: 81.047537
B29: Terminal Growth | C29: =G6 -> 0.08 | D29: =H6 -> 0.085 | E29: =I6 -> 0.09 | F29: =J6 -> 0.095
B30: =F7 -> 0.025 | C30: =G7 -> 86.331349 | D30: =H7 -> 74.730159 | E30: =I7 -> 65.014918 | F30: =J7 -> 56.775843
B31: =F8 -> 0.03 | C31: =G8 -> 93.169889 | D31: =H8 -> 80.047474 | E31: =I8 -> 69.214348 | F31: =J8 -> 60.136539
B32: =F9 -> 0.035 | C32: =G9 -> 101.52811 | D32: =H9 -> 86.428252 | E32: =I9 -> 74.17731 | F32: =J9 -> 64.057351
B33: =F10 -> 0.04 | C33: =G10 -> 111.97587 | D33: =H10 -> 94.226981 | E33: =I10 -> 80.132866 | F33: =J10 -> 68.691038
B34: =F11 -> 0.045 | C34: =G11 -> 125.40872 | D34: =H11 -> 103.97539 | E34: =I11 -> 87.411877 | F34: =J11 -> 74.251463
B35: =F12 -> 0.05 | C35: =G12 -> 143.31918 | D35: =H12 -> 116.50906 | E35: =I12 -> 96.510642 | F35: =J12 -> 81.047537

Sheet DDM
B2: Dividend Discount Model.
B3: Projected Dividends
C4: ACTUALS | M4: NEAR TERM | S4: FAR TERM
A5: # | B5: Year | C5: 2015 | D5: 2016 | E5: 2017 | F5: 2018 | G5: 2019 | H5: 2020 | I5: 2021 | J5: 2022 | K5: 2023 | L5: 2024 | M5: 2025 | N5: 2026 | O5: 2027 | P5: 2028 | Q5: 2029 | R5: 2030 | S5: 2031 | T5: 2032 | U5: 2033 | V5: 2034 | W5: 2035
B6: Quarterly Dividends | C6: 0.16 | D6: 0.2 | E6: 0.25 | F6: 0.3 | G6: 0.36 | H6: 0.41 | I6: 0.45 | J6: 0.49 | K6: 0.53 | L6: 0.57 | M6: 0.61 | N6: 0.62 | O6: =O7/4 -> 0.6355 | P6: =P7/4 -> 0.6513875 | Q6: =Q7/4 -> 0.66767219 | R6: =R7/4 -> 0.68436399 | S6: =S7/4 -> 0.70489491 | T6: =T7/4 -> 0.72604176 | U6: =U7/4 -> 0.74782301 | V6: =V7/4 -> 0.7702577 | W6: =W7/4 -> 0.80877059
B7: Annual Dividends | C7: =C6*3 -> 0.48 | D7: =D6*4 -> 0.8 | E7: =E6*4 -> 1 | F7: =F6*4 -> 1.2 | G7: =G6*4 -> 1.44 | H7: =H6*4 -> 1.64 | I7: =I6*4 -> 1.8 | J7: =J6*4 -> 1.96 | K7: =K6*4 -> 2.12 | ... N7: =N6*4 -> 2.48 | O7: =N7*(1+O8) -> 2.542 | P7: =O7*(1+P8) -> 2.60555 | Q7: =P7*(1+Q8) -> 2.6706887 | R7: =Q7*(1+R8) -> 2.737456 | S7: =R7*(1+S8) -> 2.8195796 | T7: =S7*(1+T8) -> 2.904167 | U7: =T7*(1+U8) -> 2.991292 | V7: =U7*(1+V8) -> 3.0810308 | W7: =V7*(1+W8) -> 3.2350824
B8: Growth Rate | C8: 0 | D8: =D7/C7-1 -> 0.66666667 | E8: =E7/D7-1 -> 0.25 | F8: =F7/E7-1 -> 0.2 | G8: =G7/F7-1 -> 0.2 | H8: =H7/G7-1 -> 0.13888889 | I8: =I7/H7-1 -> 0.097560976 | J8: =J7/I7-1 -> 0.088888889 | K8: =K7/J7-1 -> 0.081632653 | ... N8: =N7/M7-1 -> 0.016393443 | O8: 0.025 | P8: 0.025 | Q8: 0.025 | R8: 0.025 | S8: 0.03 | T8: 0.03 | U8: 0.03 | V8: 0.03 | W8: 0.05
B9: Buyback Yield | M9: 0.018 | N9: 0.018 | O9: 0.018 | P9: 0.018 | Q9: 0.018 | R9: 0.018 | S9: 0.018 | T9: 0.018 | U9: 0.018 | V9: 0.018 | W9: 0.018
B10: Buyback per share | M10: =$C$32*$C$31 -> 1.5552 | N10: =$C$32*$C$31 -> 1.5552 | O10: =$C$32*$C$31 -> 1.5552 | P10: =$C$32*$C$31 -> 1.5552 | Q10: =$C$32*$C$31 -> 1.5552 | R10: =$C$32*$C$31 -> 1.5552 | S10: =$C$32*$C$31 -> 1.5552 | T10: =$C$32*$C$31 -> 1.5552 | ... W10: =$C$32*$C$31 -> 1.5552
B11: Effective Dividend | M11: =M10+M7 -> 3.9952 | N11: =N10+N7 -> 4.0352 | O11: =O10+O7 -> 4.0972 | P11: =P10+P7 -> 4.16075 | Q11: =Q10+Q7 -> 4.2258887 | R11: =R10+R7 -> 4.292656 | S11: =S10+S7 -> 4.3747796 | T11: =T10+T7 -> 4.459367 | ... V11: =V10+V7 -> 4.6362308 | W11: =W7+W10 -> 4.7902824
B12: Discount factor | M12: =1/(1+$C$19)^1 -> 0.93274881 | N12: =1/(1+$C$19)^2 -> 0.87002034 | O12: =1/(1+$C$19)^3 -> 0.81151044 | P12: =1/(1+$C$19)^4 -> 0.7569354 | Q12: =1/(1+$C$19)^5 -> 0.70603059 | R12: =1/(1+$C$19)^6 -> 0.6585492 | S12: =1/(1+$C$19)^7 -> 0.61426098 | T12: =1/(1+$C$19)^8 -> 0.5729512 | U12: =1/(1+$C$19)^9 -> 0.53441955 | V12: =1/(1+$C$19)^10 -> 0.4984792 | W12: =1/(1+$C$19)^11 -> 0.46495588
B13: PV of Effective Dividend | M13: =M11*M12 -> 3.726518 | N13: =M12*N11 -> 3.763828 | O13: =N12*O11 -> 3.5646474 | P13: =O12*P11 -> 3.3764921 | Q13: =P12*Q11 -> 3.1987248 | R13: =Q12*R11 -> 3.0307464 | S13: =R12*S11 -> 2.8810076 | T13: =S12*T11 -> 2.7392152 | U13: =T12*U11 -> 2.6049181 | ... W13: =V12*W11 -> 2.3878561
B15: PARAMETERS | C15: VALUE | E15: RESULT
B16: Sum of effective dividend | C16: =SUM(M13:W13) -> 33.751646 | E16: ACTUAL PRICE | F16: =C31 -> 86.4
B17: Dividend (2035) | C17: =W11 -> 4.7902824 | E17: INTRINSIC VALUE | F17: =C23 -> 91.294509 | G17: SLIGHTLY UNDERVALUED
B18: Stable Growth (g) | C18: 0.045 | G18: HOLD
B19: Ke | C19: =C30 -> 0.0721
B20: Terminal Value (2034) | C20: =C17/(C19-C18) -> 176.76319
B21: PV of Terminal Value | C21: =C20/(1+C19)^10 -> 88.112771
B22: BuyBack Yield | C22: =C32*C20 -> 3.1817374
B23: Intrinsic Value | C23: =C21+C22 -> 91.294509
B25: PARAMETERS | C25: VALUE
B26: Beta | C26: 0.7
B27: Rf | C27: 0.007 | D27: Average of US 10 year bond yield from investing .com
B28: Rm | C28: 0.1 | D28: Long term S&P 500 average total return
B29: Rm-rf | C29: =C28-C27 -> 0.093 | D29: Market premium
B30: Ke | C30: =C27+C26*(C29) -> 0.0721
B31: Actual Price | C31: 86.4
B32: Buyback | C32: 0.018
B34: Assumptions
B35: Why Dividend Growth Dropped (7.02% → 1.64%)
B36: The slowdown in Starbucks’ dividend growth from 7.02% (2025E) to 1.64% (2026E) reflects strategic reinvestment and cost pressures rather than financial weakness.
B37: · Capital Reallocation – More funds directed toward expansion, “Greener Stores,” and digital upgrades.
B38: · Margin Pressure – Higher labor and commodity costs limit short-term free cash flow.
B39: · Stable Payout Ratio – Management maintains a ~50–60% payout, so slower earnings growth naturally lowers dividend growth.
B40: · Balanced Capital Returns – Focus may shift temporarily toward share buybacks over dividend increases.
B41: In short: Starbucks is preserving cash for growth and stability — a strategic pause, not a pullback in shareholder value
